Workbook

Sheet Dashboard
A1: FIELD FORCE & TRADE MARKETING PERFORMANCE DASHBOARD
A2: Market Express | Real sales data (Kaggle Parch & Posey) + simulated field-execution layer
A4: TOTAL SALES | D4: SALES ACHIEVEMENT | G4: VISIT COMPLETION | J4: MERCHANDISING | M4: AVAILABILITY
A6: =SUM(tblGapAnalysis[Total_Actual_Sales]) -> 8574894.9 | D6: =SUM(tblGapAnalysis[Total_Actual_Sales])/SUM(tblGapAnalysis[Total_Target]) -> 0.91920244 | G6: =SUM(tblGapAnalysis[Total_Completed_Visits])/SUM(tblGapAnalysis[Total_Planned_Visits]) -> 0.79386333 | J6: =AVERAGE(tblGapAnalysis[Avg_Merchandising]) -> 0.73519248 | M6: =AVERAGE(tblGapAnalysis[Avg_Availability]) -> 0.76488368
A60: CHART SOURCE DATA (auto-calculated - do not delete)
A62: Region_Summary
A63: Region | B63: Total_Sales | C63: Total_Target | D63: Achievement
A64: Northeast | B64: =SUMIF(tblGapAnalysis[Region],A64,tblGapAnalysis[Total_Actual_Sales]) -> 2968473.8 | C64: =SUMIF(tblGapAnalysis[Region],A64,tblGapAnalysis[Total_Target]) -> 2979022 | D64: =B64/C64 -> 0.99645918
A65: Midwest | B65: =SUMIF(tblGapAnalysis[Region],A65,tblGapAnalysis[Total_Actual_Sales]) -> 1021466.9 | C65: =SUMIF(tblGapAnalysis[Region],A65,tblGapAnalysis[Total_Target]) -> 1305074.8 | D65: =B65/C65 -> 0.78268837
A66: Southeast | B66: =SUMIF(tblGapAnalysis[Region],A66,tblGapAnalysis[Total_Actual_Sales]) -> 2330481.5 | C66: =SUMIF(tblGapAnalysis[Region],A66,tblGapAnalysis[Total_Target]) -> 2391035.3 | D66: =B66/C66 -> 0.97467468
A67: West | B67: =SUMIF(tblGapAnalysis[Region],A67,tblGapAnalysis[Total_Actual_Sales]) -> 2254472.7 | C67: =SUMIF(tblGapAnalysis[Region],A67,tblGapAnalysis[Total_Target]) -> 2653493 | D67: =B67/C67 -> 0.84962453
A70: Monthly_Sales_Trend (all order history)
A71: Year | B71: Month_Num | C71: Label | D71: Total_Sales
A72: 2013 | B72: 12 | C72: =TEXT(DATE(A72,B72,1),"mmm-yy") -> Dec-13 | D72: =SUMIFS(tblCleanOrders[Sales_USD],tblCleanOrders[Year],A72,tblCleanOrders[Month],B72) -> 177253.97
A73: 2014 | B73: 1 | C73: =TEXT(DATE(A73,B73,1),"mmm-yy") -> Jan-14 | D73: =SUMIFS(tblCleanOrders[Sales_USD],tblCleanOrders[Year],A73,tblCleanOrders[Month],B73) -> 122885.95
A74: 2014 | B74: 2 | C74: =TEXT(DATE(A74,B74,1),"mmm-yy") -> Feb-14 | D74: =SUMIFS(tblCleanOrders[Sales_USD],tblCleanOrders[Year],A74,tblCleanOrders[Month],B74) -> 131403.48
A75: 2014 | B75: 3 | C75: =TEXT(DATE(A75,B75,1),"mmm-yy") -> Mar-14 | D75: =SUMIFS(tblCleanOrders[Sales_USD],tblCleanOrders[Year],A75,tblCleanOrders[Month],B75) -> 120550.45
A76: 2014 | B76: 4 | C76: =TEXT(DATE(A76,B76,1),"mmm-yy") -> Apr-14 | D76: =SUMIFS(tblCleanOrders[Sales_USD],tblCleanOrders[Year],A76,tblCleanOrders[Month],B76) -> 129531.54
A77: 2014 | B77: 5 | C77: =TEXT(DATE(A77,B77,1),"mmm-yy") -> May-14 | D77: =SUMIFS(tblCleanOrders[Sales_USD],tblCleanOrders[Year],A77,tblCleanOrders[Month],B77) -> 135189.54
A78: 2014 | B78: 6 | C78: =TEXT(DATE(A78,B78,1),"mmm-yy") -> Jun-14 | D78: =SUMIFS(tblCleanOrders[Sales_USD],tblCleanOrders[Year],A78,tblCleanOrders[Month],B78) -> 141307.68
A79: 2014 | B79: 7 | C79: =TEXT(DATE(A79,B79,1),"mmm-yy") -> Jul-14 | D79: =SUMIFS(tblCleanOrders[Sales_USD],tblCleanOrders[Year],A79,tblCleanOrders[Month],B79) -> 143000.86
A80: 2014 | B80: 8 | C80: =TEXT(DATE(A80,B80,1),"mmm-yy") -> Aug-14 | D80: =SUMIFS(tblCleanOrders[Sales_USD],tblCleanOrders[Year],A80,tblCleanOrders[Month],B80) -> 144575.8
A81: 2014 | B81: 9 | C81: =TEXT(DATE(A81,B81,1),"mmm-yy") -> Sep-14 | D81: =SUMIFS(tblCleanOrders[Sales_USD],tblCleanOrders[Year],A81,tblCleanOrders[Month],B81) -> 138001.5
A82: 2014 | B82: 10 | C82: =TEXT(DATE(A82,B82,1),"mmm-yy") -> Oct-14 | D82: =SUMIFS(tblCleanOrders[Sales_USD],tblCleanOrders[Year],A82,tblCleanOrders[Month],B82) -> 170563.92
A83: 2014 | B83: 11 | C83: =TEXT(DATE(A83,B83,1),"mmm-yy") -> Nov-14 | D83: =SUMIFS(tblCleanOrders[Sales_USD],tblCleanOrders[Year],A83,tblCleanOrders[Month],B83) -> 143850.71
... A109: 2017 | B109: 1 | C109: =TEXT(DATE(A109,B109,1),"mmm-yy") -> Jan-17 | D109: =SUMIFS(tblCleanOrders[Sales_USD],tblCleanOrders[Year],A109,tblCleanOrders[Month],B109) -> 23424.03
A112: Top_10_Reps_by_Sales
A113: Rep_Name | B113: Total_Sales
A114: =Rep_Performance!B2 -> Earlie Schleusner | B114: =Rep_Performance!D2 -> 506470.92
A115: =Rep_Performance!B3 -> Moon Torian | B115: =Rep_Performance!D3 -> 474372.08
A116: =Rep_Performance!B4 -> Vernita Plump | B116: =Rep_Performance!D4 -> 472044.16
A117: =Rep_Performance!B5 -> Tia Amato | B117: =Rep_Performance!D5 -> 466213.64
A118: =Rep_Performance!B6 -> Dawna Agnew | B118: =Rep_Performance!D6 -> 410948.92
A119: =Rep_Performance!B7 -> Maryanna Fiorentino | B119: =Rep_Performance!D7 -> 363890.51
A120: =Rep_Performance!B8 -> Nelle Meaux | B120: =Rep_Performance!D8 -> 359779.88
A121: =Rep_Performance!B9 -> Elwood Shutt | B121: =Rep_Performance!D9 -> 346698.05
A122: =Rep_Performance!B10 -> Delilah Krum | B122: =Rep_Performance!D10 -> 315747.89
A123: =Rep_Performance!B11 -> Charles Bidwell | B123: =Rep_Performance!D11 -> 306753.04
A126: Bottom_10_Reps_by_Achievement
A127: Rep_Name | B127: Sales_Achievement
A128: =INDEX(tblGapAnalysis[Rep_Name],MATCH(321670,tblGapAnalysis[Rep_ID],0)) -> Nakesha Renn | B128: =INDEX(tblGapAnalysis[Sales_Achievement],MATCH(321670,tblGapAnalysis[Rep_ID],0)) -> 0.18122508
A129: =INDEX(tblGapAnalysis[Rep_Name],MATCH(321730,tblGapAnalysis[Rep_ID],0)) -> Carletta Kosinski | B129: =INDEX(tblGapAnalysis[Sales_Achievement],MATCH(321730,tblGapAnalysis[Rep_ID],0)) -> 0.22785908
A130: =INDEX(tblGapAnalysis[Rep_Name],MATCH(321770,tblGapAnalysis[Rep_ID],0)) -> Kathleen Lalonde | B130: =INDEX(tblGapAnalysis[Sales_Achievement],MATCH(321770,tblGapAnalysis[Rep_ID],0)) -> 0.29090909
A131: =INDEX(tblGapAnalysis[Rep_Name],MATCH(321900,tblGapAnalysis[Rep_ID],0)) -> Soraya Fulton | B131: =INDEX(tblGapAnalysis[Sales_Achievement],MATCH(321900,tblGapAnalysis[Rep_ID],0)) -> 0.32774945
A132: =INDEX(tblGapAnalysis[Rep_Name],MATCH(321780,tblGapAnalysis[Rep_ID],0)) -> Julie Starr | B132: =INDEX(tblGapAnalysis[Sales_Achievement],MATCH(321780,tblGapAnalysis[Rep_ID],0)) -> 0.44036621
A133: =INDEX(tblGapAnalysis[Rep_Name],MATCH(321920,tblGapAnalysis[Rep_ID],0)) -> Marquetta Laycock | B133: =INDEX(tblGapAnalysis[Sales_Achievement],MATCH(321920,tblGapAnalysis[Rep_ID],0)) -> 0.50853614
A134: =INDEX(tblGapAnalysis[Rep_Name],MATCH(321880,tblGapAnalysis[Rep_ID],0)) -> Babette Soukup | B134: =INDEX(tblGapAnalysis[Sales_Achievement],MATCH(321880,tblGapAnalysis[Rep_ID],0)) -> 0.54376514
A135: =INDEX(tblGapAnalysis[Rep_Name],MATCH(321660,tblGapAnalysis[Rep_ID],0)) -> Silvana Virden | B135: =INDEX(tblGapAnalysis[Sales_Achievement],MATCH(321660,tblGapAnalysis[Rep_ID],0)) -> 0.61818182
A136: =INDEX(tblGapAnalysis[Rep_Name],MATCH(321620,tblGapAnalysis[Rep_ID],0)) -> Retha Sears | B136: =INDEX(tblGapAnalysis[Sales_Achievement],MATCH(321620,tblGapAnalysis[Rep_ID],0)) -> 0.65526028
A137: =INDEX(tblGapAnalysis[Rep_Name],MATCH(321930,tblGapAnalysis[Rep_ID],0)) -> Hilma Busick | B137: =INDEX(tblGapAnalysis[Sales_Achievement],MATCH(321930,tblGapAnalysis[Rep_ID],0)) -> 0.68790731

Sheet Final_Report
B1: FINAL REPORT — EXECUTIVE SUMMARY
B2: Field Force & Trade Marketing Performance Dashboard | Market Express | Real sales data (Kaggle Parch & Posey) + simulated field-execution layer
B4: PERFORMANCE SNAPSHOT
B5: TOTAL SALES | C5: SALES ACHIEVEMENT | D5: VISIT COMPLETION | E5: AVG MERCHANDISING | F5: AVG AVAILABILITY
B6: =SUM(tblGapAnalysis[Total_Actual_Sales]) -> 8574894.9 | C6: =SUM(tblGapAnalysis[Total_Actual_Sales])/SUM(tblGapAnalysis[Total_Target]) -> 0.91920244 | D6: =SUM(tblGapAnalysis[Total_Completed_Visits])/SUM(tblGapAnalysis[Total_Planned_Visits]) -> 0.79386333 | E6: =AVERAGE(tblGapAnalysis[Avg_Merchandising]) -> 0.73519248 | F6: =AVERAGE(tblGapAnalysis[Avg_Availability]) -> 0.76488368
B8: REP STATUS MIX
B9: HEALTHY | C9: AT RISK | D9: CRITICAL
B10: =COUNTIF(tblGapAnalysis[Status],"Healthy") -> 16 | C10: =COUNTIF(tblGapAnalysis[Status],"At Risk") -> 9 | D10: =COUNTIF(tblGapAnalysis[Status],"Critical") -> 25 | E10: ="out of "&COUNTA(tblGapAnalysis[Rep_ID])&" reps" -> out of 50 reps
B12: EXECUTIVE SUMMARY
B13: Across 50 sales representatives and 25 months (Jan 2015-Jan 2017), Market Express reached roughly 92% of its combined sales target, but that headline figure hides a wide spread: half the sales force (25 of 50 reps) is flagged At Risk or Critical, and 25 reps are Critical on both commercial and execution metrics at once. Visit completion (79%) is materially weaker than attendance, and average merchandising compliance (74%) and product availability (76%) both sit well below their 90% and 95% targets - the field-execution layer is the more consistent shortfall across the business, not sales alone. The sections below separate reps whose shortfall looks commercial (sales gap, healthy execution) from reps whose shortfall looks operational (sales gap plus weak visits/merchandising/availability), so management can route each case to the right team.
B15: REGIONAL PERFORMANCE
B16: Region | C16: Total Sales | D16: Total Target | E16: Sales Gap | F16: Achievement % | G16: Avg Merchandising
B17: Northeast | C17: =SUMIF(tblGapAnalysis[Region],B17,tblGapAnalysis[Total_Actual_Sales]) -> 2968473.8 | D17: =SUMIF(tblGapAnalysis[Region],B17,tblGapAnalysis[Total_Target]) -> 2979022 | E17: =C17-D17 -> -10548.183 | F17: =C17/D17 -> 0.99645918 | G17: =AVERAGEIF(tblGapAnalysis[Region],B17,tblGapAnalysis[Avg_Merchandising]) -> 0.71291905
B18: Midwest | C18: =SUMIF(tblGapAnalysis[Region],B18,tblGapAnalysis[Total_Actual_Sales]) -> 1021466.9 | D18: =SUMIF(tblGapAnalysis[Region],B18,tblGapAnalysis[Total_Target]) -> 1305074.8 | E18: =C18-D18 -> -283607.94 | F18: =C18/D18 -> 0.78268837 | G18: =AVERAGEIF(tblGapAnalysis[Region],B18,tblGapAnalysis[Avg_Merchandising]) -> 0.74890711
B19: Southeast | C19: =SUMIF(tblGapAnalysis[Region],B19,tblGapAnalysis[Total_Actual_Sales]) -> 2330481.5 | D19: =SUMIF(tblGapAnalysis[Region],B19,tblGapAnalysis[Total_Target]) -> 2391035.3 | E19: =C19-D19 -> -60553.734 | F19: =C19/D19 -> 0.97467468 | G19: =AVERAGEIF(tblGapAnalysis[Region],B19,tblGapAnalysis[Avg_Merchandising]) -> 0.7237572
B20: West | C20: =SUMIF(tblGapAnalysis[Region],B20,tblGapAnalysis[Total_Actual_Sales]) -> 2254472.7 | D20: =SUMIF(tblGapAnalysis[Region],B20,tblGapAnalysis[Total_Target]) -> 2653493 | E20: =C20-D20 -> -399020.25 | F20: =C20/D20 -> 0.84962453 | G20: =AVERAGEIF(tblGapAnalysis[Region],B20,tblGapAnalysis[Avg_Merchandising]) -> 0.7810588
B22: TOP 5 REPS BY SALES GAP (AHEAD OF TARGET)
B23: Rep Name | C23: Region | D23: Sales Gap | E23: Achievement % | F23: Status
B24: =INDEX(tblGapAnalysis[Rep_Name],MATCH(LARGE(tblGapAnalysis[Sales_Gap],1),tblGapAnalysis[Sales_Gap],0)) -> Elwood Shutt | C24: =INDEX(tblGapAnalysis[Region],MATCH(LARGE(tblGapAnalysis[Sales_Gap],1),tblGapAnalysis[Sales_Gap],0)) -> West | D24: =LARGE(tblGapAnalysis[Sales_Gap],1) -> 65367.013 | E24: =INDEX(tblGapAnalysis[Sales_Achievement],MATCH(LARGE(tblGapAnalysis[Sales_Gap],1),tblGapAnalysis[Sales_Gap],0)) -> 1.2539512 | F24: =INDEX(tblGapAnalysis[Status],MATCH(LARGE(tblGapAnalysis[Sales_Gap],1),tblGapAnalysis[Sales_Gap],0)) -> At Risk
B25: =INDEX(tblGapAnalysis[Rep_Name],MATCH(LARGE(tblGapAnalysis[Sales_Gap],2),tblGapAnalysis[Sales_Gap],0)) -> Maryanna Fiorentino | C25: =INDEX(tblGapAnalysis[Region],MATCH(LARGE(tblGapAnalysis[Sales_Gap],2),tblGapAnalysis[Sales_Gap],0)) -> West | D25: =LARGE(tblGapAnalysis[Sales_Gap],2) -> 59823.22 | E25: =INDEX(tblGapAnalysis[Sales_Achievement],MATCH(LARGE(tblGapAnalysis[Sales_Gap],2),tblGapAnalysis[Sales_Gap],0)) -> 1.2266749 | F25: =INDEX(tblGapAnalysis[Status],MATCH(LARGE(tblGapAnalysis[Sales_Gap],2),tblGapAnalysis[Sales_Gap],0)) -> Healthy
B26: =INDEX(tblGapAnalysis[Rep_Name],MATCH(LARGE(tblGapAnalysis[Sales_Gap],3),tblGapAnalysis[Sales_Gap],0)) -> Arica Stoltzfus | C26: =INDEX(tblGapAnalysis[Region],MATCH(LARGE(tblGapAnalysis[Sales_Gap],3),tblGapAnalysis[Sales_Gap],0)) -> West | D26: =LARGE(tblGapAnalysis[Sales_Gap],3) -> 54616.838 | E26: =INDEX(tblGapAnalysis[Sales_Achievement],MATCH(LARGE(tblGapAnalysis[Sales_Gap],3),tblGapAnalysis[Sales_Gap],0)) -> 1.3076714 | F26: =INDEX(tblGapAnalysis[Status],MATCH(LARGE(tblGapAnalysis[Sales_Gap],3),tblGapAnalysis[Sales_Gap],0)) -> At Risk
B27: =INDEX(tblGapAnalysis[Rep_Name],MATCH(LARGE(tblGapAnalysis[Sales_Gap],4),tblGapAnalysis[Sales_Gap],0)) -> Vernita Plump | C27: =INDEX(tblGapAnalysis[Region],MATCH(LARGE(tblGapAnalysis[Sales_Gap],4),tblGapAnalysis[Sales_Gap],0)) -> Southeast | D27: =LARGE(tblGapAnalysis[Sales_Gap],4) -> 49203.456 | E27: =INDEX(tblGapAnalysis[Sales_Achievement],MATCH(LARGE(tblGapAnalysis[Sales_Gap],4),tblGapAnalysis[Sales_Gap],0)) -> 1.1403964 | F27: =INDEX(tblGapAnalysis[Status],MATCH(LARGE(tblGapAnalysis[Sales_Gap],4),tblGapAnalysis[Sales_Gap],0)) -> Healthy
B28: =INDEX(tblGapAnalysis[Rep_Name],MATCH(LARGE(tblGapAnalysis[Sales_Gap],5),tblGapAnalysis[Sales_Gap],0)) -> Necole Victory | C28: =INDEX(tblGapAnalysis[Region],MATCH(LARGE(tblGapAnalysis[Sales_Gap],5),tblGapAnalysis[Sales_Gap],0)) -> Northeast | D28: =LARGE(tblGapAnalysis[Sales_Gap],5) -> 39607.853 | E28: =INDEX(tblGapAnalysis[Sales_Achievement],MATCH(LARGE(tblGapAnalysis[Sales_Gap],5),tblGapAnalysis[Sales_Gap],0)) -> 1.2250178 | F28: =INDEX(tblGapAnalysis[Status],MATCH(LARGE(tblGapAnalysis[Sales_Gap],5),tblGapAnalysis[Sales_Gap],0)) -> Critical
B30: BOTTOM 5 REPS BY SALES GAP (FURTHEST BELOW TARGET)
B31: Rep Name | C31: Region | D31: Sales Gap | E31: Achievement % | F31: Status
B32: =INDEX(tblGapAnalysis[Rep_Name],MATCH(SMALL(tblGapAnalysis[Sales_Gap],1),tblGapAnalysis[Sales_Gap],0)) -> Soraya Fulton | C32: =INDEX(tblGapAnalysis[Region],MATCH(SMALL(tblGapAnalysis[Sales_Gap],1),tblGapAnalysis[Sales_Gap],0)) -> West | D32: =SMALL(tblGapAnalysis[Sales_Gap],1) -> -336745.54 | E32: =INDEX(tblGapAnalysis[Sales_Achievement],MATCH(SMALL(tblGapAnalysis[Sales_Gap],1),tblGapAnalysis[Sales_Gap],0)) -> 0.32774945 | F32: =INDEX(tblGapAnalysis[Status],MATCH(SMALL(tblGapAnalysis[Sales_Gap],1),tblGapAnalysis[Sales_Gap],0)) -> Critical
B33: =INDEX(tblGapAnalysis[Rep_Name],MATCH(SMALL(tblGapAnalysis[Sales_Gap],2),tblGapAnalysis[Sales_Gap],0)) -> Kathleen Lalonde | C33: =INDEX(tblGapAnalysis[Region],MATCH(SMALL(tblGapAnalysis[Sales_Gap],2),tblGapAnalysis[Sales_Gap],0)) -> Midwest | D33: =SMALL(tblGapAnalysis[Sales_Gap],2) -> -107017.24 | E33: =INDEX(tblGapAnalysis[Sales_Achievement],MATCH(SMALL(tblGapAnalysis[Sales_Gap],2),tblGapAnalysis[Sales_Gap],0)) -> 0.29090909 | F33: =INDEX(tblGapAnalysis[Status],MATCH(SMALL(tblGapAnalysis[Sales_Gap],2),tblGapAnalysis[Sales_Gap],0)) -> Critical
B34: =INDEX(tblGapAnalysis[Rep_Name],MATCH(SMALL(tblGapAnalysis[Sales_Gap],3),tblGapAnalysis[Sales_Gap],0)) -> Marquetta Laycock | C34: =INDEX(tblGapAnalysis[Region],MATCH(SMALL(tblGapAnalysis[Sales_Gap],3),tblGapAnalysis[Sales_Gap],0)) -> West | D34: =SMALL(tblGapAnalysis[Sales_Gap],3) -> -88461.817 | E34: =INDEX(tblGapAnalysis[Sales_Achievement],MATCH(SMALL(tblGapAnalysis[Sales_Gap],3),tblGapAnalysis[Sales_Gap],0)) -> 0.50853614 | F34: =INDEX(tblGapAnalysis[Status],MATCH(SMALL(tblGapAnalysis[Sales_Gap],3),tblGapAnalysis[Sales_Gap],0)) -> Critical
B35: =INDEX(tblGapAnalysis[Rep_Name],MATCH(SMALL(tblGapAnalysis[Sales_Gap],4),tblGapAnalysis[Sales_Gap],0)) -> Dawna Agnew | C35: =INDEX(tblGapAnalysis[Region],MATCH(SMALL(tblGapAnalysis[Sales_Gap],4),tblGapAnalysis[Sales_Gap],0)) -> West | D35: =SMALL(tblGapAnalysis[Sales_Gap],4) -> -80403.05 | E35: =INDEX(tblGapAnalysis[Sales_Achievement],MATCH(SMALL(tblGapAnalysis[Sales_Gap],4),tblGapAnalysis[Sales_Gap],0)) -> 0.83636364 | F35: =INDEX(tblGapAnalysis[Status],MATCH(SMALL(tblGapAnalysis[Sales_Gap],4),tblGapAnalysis[Sales_Gap],0)) -> At Risk
B36: =INDEX(tblGapAnalysis[Rep_Name],MATCH(SMALL(tblGapAnalysis[Sales_Gap],5),tblGapAnalysis[Sales_Gap],0)) -> Carletta Kosinski | C36: =INDEX(tblGapAnalysis[Region],MATCH(SMALL(tblGapAnalysis[Sales_Gap],5),tblGapAnalysis[Sales_Gap],0)) -> Midwest | D36: =SMALL(tblGapAnalysis[Sales_Gap],5) -> -78888.715 | E36: =INDEX(tblGapAnalysis[Sales_Achievement],MATCH(SMALL(tblGapAnalysis[Sales_Gap],5),tblGapAnalysis[Sales_Gap],0)) -> 0.22785908 | F36: =INDEX(tblGapAnalysis[Status],MATCH(SMALL(tblGapAnalysis[Sales_Gap],5),tblGapAnalysis[Sales_Gap],0)) -> Critical
B38: KEY FINDINGS
B39: • Overall achievement (~92%) looks close to target, but that average masks a bimodal sales force: 16 reps are Healthy, 9 are At Risk, and 25 - half the team - are Critical. A single company-wide average would have hidden this split.
B40: • Northeast (99.6%) and Southeast (97.5%) are close to target as regions, while Midwest (78.3%) and West (85.0%) lag on sales achievement. Merchandising compliance does not track the same ranking, though: Northeast, the top-achieving region on sales, has the lowest average merchandising compliance of the four regions (71.3%), while West, the second-weakest region on sales, has the highest (78.1%). Regional sales performance and regional execution quality are not moving together.
B41: • Visit completion (79%) trails attendance, and both average merchandising compliance (74%) and product availability (76%) sit roughly 15-20 percentage points below their 90%/95% targets across the whole sales force - execution quality, not just visit volume, is the more common shortfall.
B42: • The relationship between merchandising compliance and sales achievement is positive but weak (correlation ~0.22) at the whole-portfolio level. That means execution quality is not the whole story: some reps with strong merchandising still miss target, and some reps hit target despite weak execution, so each Critical rep needs to be read individually rather than assumed to be one root cause.
B43: • A distinct subset of reps combines a large negative Sales Gap with merchandising and availability both below ~75% (e.g. Marquetta Laycock, Carletta Kosinski, Nakesha Renn, Babette Soukup, Derrick Boggess) - for these reps, weak field execution is plausibly contributing to the sales shortfall.
B44: • At least one rep (Soraya Fulton, West) shows a large negative Sales Gap (-$337K, 33% achievement) while merchandising and availability are both healthy (88-91%) - this looks like a commercial issue (territory, pricing, account mix) rather than a field-execution problem.
B46: FINDINGS → RECOMMENDATIONS
B47: Finding | E47: Recommended Action
B48: Reps flagged Critical with low merchandising AND low availability (e.g. Marquetta Laycock, Carletta Kosinski, Nakesha Renn) show weak execution alongside weak sales. | E48: Prioritize merchandising audits and supervisor ride-alongs for these reps before adding visit volume; pair with a supply/availability check at their outlets.
B49: Reps with a large Sales Gap but healthy execution metrics near target (e.g. Soraya Fulton) point to a non-execution cause. | E49: Investigate commercially: pricing, account mix, territory potential, and competitive activity, rather than routing these reps into field-execution coaching.
B50: Visit completion (79%) is the weakest attendance-adjacent metric, and merchandising/availability trail it further. | E50: Shift the field-force conversation from 'how many visits' to 'what happens during the visit' - audit visit quality and outlet-level compliance, not just completion counts.
B51: Midwest is the lowest-achieving region on sales, but Northeast - the highest-achieving region - has the weakest average merchandising compliance of the four. Regional sales rank and regional execution rank do not line up. | E51: Run separate regional reviews: a commercial deep-dive on Midwest (target-setting, staffing, account potential) and a merchandising-standards review in Northeast, rather than assuming one regional cause explains both patterns.
B52: 25 of 50 reps are Critical - a scale that a handful of one-off interventions will not fix. | E52: Segment the Critical group by root cause (commercial vs. execution, per the split above) and run two separate management tracks rather than one generic improvement plan.
B54: DATA LIMITATIONS
B55: Sales, accounts, sales-rep and region data are real, drawn from the public Kaggle 'Sales Dataset of Different Regions' (Parch & Posey schema). Field-force operational metrics - attendance, planned/completed visits, merchandising compliance and product availability - were SIMULATED for portfolio purposes (see Operational_Data and README) and should not be interpreted as real Market Express figures. Targets are a portfolio assumption (historical average monthly sales x a rising multiplier), not an actual company-set target. Findings and recommendations above are illustrative of the analysis approach, not verified business decisions.

Sheet README
A1: Field Force & Trade Marketing Performance Dashboard
A3: BUSINESS PROBLEM
A4: Market Express needs visibility into which regions and sales representatives are underperforming, and whether shortfalls are driven by weak selling, poor field execution (visits, merchandising, availability), or both.
A6: OBJECTIVE
A7: Combine real commercial data with a field-execution layer to answer: Which reps/regions are below target? Is the gap commercial or operational? Where should management focus attention?
A9: DATASET
A10: Real data: orders.csv, accounts.csv, sales_reps.csv, region.csv — the 'Sales Dataset of Different Regions' (Parch & Posey schema) from Kaggle. Contains 4,050 orders, 351 accounts, 50 sales reps, 4 regions, spanning Dec 2013–Jan 2017.
A11: Simulated data: field_force_operational_data.xlsx — Working_Days, Attendance_Days, Planned_Visits, Completed_Visits, Merchandising_Compliance, Product_Availability, Target_Multiplier for 50 reps x 25 months (Jan 2015–Jan 2017). This layer does not exist in the public dataset and was built to demonstrate how an analyst would combine commercial and field-execution data.
A13: DATA MODEL
A14: Region -> Sales Rep -> Account -> Order (via region_id, sales_rep_id, account_id foreign keys).
A16: WORKBOOK STRUCTURE
A17: Raw_Orders / Raw_Accounts / Raw_Reps / Raw_Regions — unmodified source tables, loaded as Excel Tables.
... A43: The public dataset contains sales, accounts, regions and sales representative information only. Field-force operational metrics (attendance, planned/completed visits, merchandising compliance, product availability) were SIMULATED for portfolio purposes and should not be interpreted as real Market Express data. All simulated cells are shown in blue font throughout the workbook. Real, formula-derived cells are black.

Sheet Gap_Analysis
A1: Rep_ID | B1: Rep_Name | C1: Region | D1: Total_Actual_Sales | E1: Total_Target | F1: Sales_Gap | G1: Sales_Achievement | H1: Total_Completed_Visits | I1: Total_Planned_Visits | J1: Visit_Gap | K1: Visit_Completion_Rate | L1: Avg_Merchandising | M1: Merchandising_Gap | N1: Avg_Availability | O1: Availability_Gap | P1: Status
A2: =Raw_Reps!A42 -> 321900 | B2: =Raw_Reps!B42 -> Soraya Fulton | C2: =INDEX(tblRegions[name],MATCH(Raw_Reps!C42,tblRegions[id],0)) -> West | D2: =SUMIF(tblOperational[Rep_ID],A2,tblOperational[Actual_Sales]) -> 164177.13 | E2: =SUMIF(tblOperational[Rep_ID],A2,tblOperational[Target]) -> 500922.67 | F2: =D2-E2 -> -336745.54 | G2: =IFERROR(D2/E2,0) -> 0.32774945 | H2: =SUMIF(tblOperational[Rep_ID],A2,tblOperational[Completed_Visits]) -> 12528 | I2: =SUMIF(tblOperational[Rep_ID],A2,tblOperational[Planned_Visits]) -> 13788 | J2: =H2-I2 -> -1260 | K2: =H2/I2 -> 0.90861619 | L2: =AVERAGEIF(tblOperational[Rep_ID],A2,tblOperational[Merchandising_Compliance]) -> 0.876004 | M2: =L2-0.9 -> -0.023996 | N2: =AVERAGEIF(tblOperational[Rep_ID],A2,tblOperational[Product_Availability]) -> 0.91062 | O2: =N2-0.95 -> -0.03938 | P2: =IF(AND(G2>=0.9,L2>=0.8),"Healthy",IF(OR(G2<0.8,L2<0.7),"Critical","At Risk")) -> Critical
A3: =Raw_Reps!A29 -> 321770 | B3: =Raw_Reps!B29 -> Kathleen Lalonde | C3: =INDEX(tblRegions[name],MATCH(Raw_Reps!C29,tblRegions[id],0)) -> Midwest | D3: =SUMIF(tblOperational[Rep_ID],A3,tblOperational[Actual_Sales]) -> 43904.51 | E3: =SUMIF(tblOperational[Rep_ID],A3,tblOperational[Target]) -> 150921.75 | F3: =D3-E3 -> -107017.24 | G3: =IFERROR(D3/E3,0) -> 0.29090909 | H3: =SUMIF(tblOperational[Rep_ID],A3,tblOperational[Completed_Visits]) -> 12010 | I3: =SUMIF(tblOperational[Rep_ID],A3,tblOperational[Planned_Visits]) -> 14088 | J3: =H3-I3 -> -2078 | K3: =H3/I3 -> 0.85249858 | L3: =AVERAGEIF(tblOperational[Rep_ID],A3,tblOperational[Merchandising_Compliance]) -> 0.78688 | M3: =L3-0.9 -> -0.11312 | N3: =AVERAGEIF(tblOperational[Rep_ID],A3,tblOperational[Product_Availability]) -> 0.824932 | O3: =N3-0.95 -> -0.125068 | P3: =IF(AND(G3>=0.9,L3>=0.8),"Healthy",IF(OR(G3<0.8,L3<0.7),"Critical","At Risk")) -> Critical
A4: =Raw_Reps!A44 -> 321920 | B4: =Raw_Reps!B44 -> Marquetta Laycock | C4: =INDEX(tblRegions[name],MATCH(Raw_Reps!C44,tblRegions[id],0)) -> West | D4: =SUMIF(tblOperational[Rep_ID],A4,tblOperational[Actual_Sales]) -> 91534.77 | E4: =SUMIF(tblOperational[Rep_ID],A4,tblOperational[Target]) -> 179996.59 | F4: =D4-E4 -> -88461.817 | G4: =IFERROR(D4/E4,0) -> 0.50853614 | H4: =SUMIF(tblOperational[Rep_ID],A4,tblOperational[Completed_Visits]) -> 8047 | I4: =SUMIF(tblOperational[Rep_ID],A4,tblOperational[Planned_Visits]) -> 12288 | J4: =H4-I4 -> -4241 | K4: =H4/I4 -> 0.65486654 | L4: =AVERAGEIF(tblOperational[Rep_ID],A4,tblOperational[Merchandising_Compliance]) -> 0.58604 | M4: =L4-0.9 -> -0.31396 | N4: =AVERAGEIF(tblOperational[Rep_ID],A4,tblOperational[Product_Availability]) -> 0.61066 | O4: =N4-0.95 -> -0.33934 | P4: =IF(AND(G4>=0.9,L4>=0.8),"Healthy",IF(OR(G4<0.8,L4<0.7),"Critical","At Risk")) -> Critical
A5: =Raw_Reps!A51 -> 321990 | B5: =Raw_Reps!B51 -> Dawna Agnew | C5: =INDEX(tblRegions[name],MATCH(Raw_Reps!C51,tblRegions[id],0)) -> West | D5: =SUMIF(tblOperational[Rep_ID],A5,tblOperational[Actual_Sales]) -> 410948.92 | E5: =SUMIF(tblOperational[Rep_ID],A5,tblOperational[Target]) -> 491351.97 | F5: =D5-E5 -> -80403.05 | G5: =IFERROR(D5/E5,0) -> 0.83636364 | H5: =SUMIF(tblOperational[Rep_ID],A5,tblOperational[Completed_Visits]) -> 9586 | I5: =SUMIF(tblOperational[Rep_ID],A5,tblOperational[Planned_Visits]) -> 12288 | J5: =H5-I5 -> -2702 | K5: =H5/I5 -> 0.78011068 | L5: =AVERAGEIF(tblOperational[Rep_ID],A5,tblOperational[Merchandising_Compliance]) -> 0.72444 | M5: =L5-0.9 -> -0.17556 | N5: =AVERAGEIF(tblOperational[Rep_ID],A5,tblOperational[Product_Availability]) -> 0.753608 | O5: =N5-0.95 -> -0.196392 | P5: =IF(AND(G5>=0.9,L5>=0.8),"Healthy",IF(OR(G5<0.8,L5<0.7),"Critical","At Risk")) -> At Risk
A6: =Raw_Reps!A25 -> 321730 | B6: =Raw_Reps!B25 -> Carletta Kosinski | C6: =INDEX(tblRegions[name],MATCH(Raw_Reps!C25,tblRegions[id],0)) -> Midwest | D6: =SUMIF(tblOperational[Rep_ID],A6,tblOperational[Actual_Sales]) -> 23280.09 | E6: =SUMIF(tblOperational[Rep_ID],A6,tblOperational[Target]) -> 102168.8 | F6: =D6-E6 -> -78888.715 | G6: =IFERROR(D6/E6,0) -> 0.22785908 | H6: =SUMIF(tblOperational[Rep_ID],A6,tblOperational[Completed_Visits]) -> 9618 | I6: =SUMIF(tblOperational[Rep_ID],A6,tblOperational[Planned_Visits]) -> 12888 | J6: =H6-I6 -> -3270 | K6: =H6/I6 -> 0.74627561 | L6: =AVERAGEIF(tblOperational[Rep_ID],A6,tblOperational[Merchandising_Compliance]) -> 0.681952 | M6: =L6-0.9 -> -0.218048 | N6: =AVERAGEIF(tblOperational[Rep_ID],A6,tblOperational[Product_Availability]) -> 0.72588 | O6: =N6-0.95 -> -0.22412 | P6: =IF(AND(G6>=0.9,L6>=0.8),"Healthy",IF(OR(G6<0.8,L6<0.7),"Critical","At Risk")) -> Critical
A7: =Raw_Reps!A19 -> 321670 | B7: =Raw_Reps!B19 -> Nakesha Renn | C7: =INDEX(tblRegions[name],MATCH(Raw_Reps!C19,tblRegions[id],0)) -> Northeast | D7: =SUMIF(tblOperational[Rep_ID],A7,tblOperational[Actual_Sales]) -> 15717.12 | E7: =SUMIF(tblOperational[Rep_ID],A7,tblOperational[Target]) -> 86727.068 | F7: =D7-E7 -> -71009.948 | G7: =IFERROR(D7/E7,0) -> 0.18122508 | H7: =SUMIF(tblOperational[Rep_ID],A7,tblOperational[Completed_Visits]) -> 7903 | I7: =SUMIF(tblOperational[Rep_ID],A7,tblOperational[Planned_Visits]) -> 13188 | J7: =H7-I7 -> -5285 | K7: =H7/I7 -> 0.5992569 | L7: =AVERAGEIF(tblOperational[Rep_ID],A7,tblOperational[Merchandising_Compliance]) -> 0.515632 | M7: =L7-0.9 -> -0.384368 | N7: =AVERAGEIF(tblOperational[Rep_ID],A7,tblOperational[Product_Availability]) -> 0.557656 | O7: =N7-0.95 -> -0.392344 | P7: =IF(AND(G7>=0.9,L7>=0.8),"Healthy",IF(OR(G7<0.8,L7<0.7),"Critical","At Risk")) -> Critical
A8: =Raw_Reps!A45 -> 321930 | B8: =Raw_Reps!B45 -> Hilma Busick | C8: =INDEX(tblRegions[name],MATCH(Raw_Reps!C45,tblRegions[id],0)) -> West | D8: =SUMIF(tblOperational[Rep_ID],A8,tblOperational[Actual_Sales]) -> 130558.53 | E8: =SUMIF(tblOperational[Rep_ID],A8,tblOperational[Target]) -> 189790.87 | F8: =D8-E8 -> -59232.344 | G8: =IFERROR(D8/E8,0) -> 0.68790731 | H8: =SUMIF(tblOperational[Rep_ID],A8,tblOperational[Completed_Visits]) -> 10196 | I8: =SUMIF(tblOperational[Rep_ID],A8,tblOperational[Planned_Visits]) -> 12588 | J8: =H8-I8 -> -2392 | K8: =H8/I8 -> 0.80997776 | L8: =AVERAGEIF(tblOperational[Rep_ID],A8,tblOperational[Merchandising_Compliance]) -> 0.766488 | M8: =L8-0.9 -> -0.133512 | N8: =AVERAGEIF(tblOperational[Rep_ID],A8,tblOperational[Product_Availability]) -> 0.796848 | O8: =N8-0.95 -> -0.153152 | P8: =IF(AND(G8>=0.9,L8>=0.8),"Healthy",IF(OR(G8<0.8,L8<0.7),"Critical","At Risk")) -> Critical
A9: =Raw_Reps!A18 -> 321660 | B9: =Raw_Reps!B18 -> Silvana Virden | C9: =INDEX(tblRegions[name],MATCH(Raw_Reps!C18,tblRegions[id],0)) -> Northeast | D9: =SUMIF(tblOperational[Rep_ID],A9,tblOperational[Actual_Sales]) -> 94772.32 | E9: =SUMIF(tblOperational[Rep_ID],A9,tblOperational[Target]) -> 153308.16 | F9: =D9-E9 -> -58535.845 | G9: =IFERROR(D9/E9,0) -> 0.61818182 | H9: =SUMIF(tblOperational[Rep_ID],A9,tblOperational[Completed_Visits]) -> 10794 | I9: =SUMIF(tblOperational[Rep_ID],A9,tblOperational[Planned_Visits]) -> 12888 | J9: =H9-I9 -> -2094 | K9: =H9/I9 -> 0.83752328 | L9: =AVERAGEIF(tblOperational[Rep_ID],A9,tblOperational[Merchandising_Compliance]) -> 0.797132 | M9: =L9-0.9 -> -0.102868 | N9: =AVERAGEIF(tblOperational[Rep_ID],A9,tblOperational[Product_Availability]) -> 0.824884 | O9: =N9-0.95 -> -0.125116 | P9: =IF(AND(G9>=0.9,L9>=0.8),"Healthy",IF(OR(G9<0.8,L9<0.7),"Critical","At Risk")) -> Critical
A10: =Raw_Reps!A40 -> 321880 | B10: =Raw_Reps!B40 -> Babette Soukup | C10: =INDEX(tblRegions[name],MATCH(Raw_Reps!C40,tblRegions[id],0)) -> Southeast | D10: =SUMIF(tblOperational[Rep_ID],A10,tblOperational[Actual_Sales]) -> 68265.44 | E10: =SUMIF(tblOperational[Rep_ID],A10,tblOperational[Target]) -> 125542.14 | F10: =D10-E10 -> -57276.701 | G10: =IFERROR(D10/E10,0) -> 0.54376514 | H10: =SUMIF(tblOperational[Rep_ID],A10,tblOperational[Completed_Visits]) -> 8342 | I10: =SUMIF(tblOperational[Rep_ID],A10,tblOperational[Planned_Visits]) -> 13188 | J10: =H10-I10 -> -4846 | K10: =H10/I10 -> 0.63254474 | L10: =AVERAGEIF(tblOperational[Rep_ID],A10,tblOperational[Merchandising_Compliance]) -> 0.536896 | M10: =L10-0.9 -> -0.363104 | N10: =AVERAGEIF(tblOperational[Rep_ID],A10,tblOperational[Product_Availability]) -> 0.575612 | O10: =N10-0.95 -> -0.374388 | P10: =IF(AND(G10>=0.9,L10>=0.8),"Healthy",IF(OR(G10<0.8,L10<0.7),"Critical","At Risk")) -> Critical
A11: =Raw_Reps!A39 -> 321870 | B11: =Raw_Reps!B39 -> Derrick Boggess | C11: =INDEX(tblRegions[name],MATCH(Raw_Reps!C39,tblRegions[id],0)) -> Southeast | D11: =SUMIF(tblOperational[Rep_ID],A11,tblOperational[Actual_Sales]) -> 127986.57 | E11: =SUMIF(tblOperational[Rep_ID],A11,tblOperational[Target]) -> 184637.47 | F11: =D11-E11 -> -56650.898 | G11: =IFERROR(D11/E11,0) -> 0.69317767 | H11: =SUMIF(tblOperational[Rep_ID],A11,tblOperational[Completed_Visits]) -> 8155 | I11: =SUMIF(tblOperational[Rep_ID],A11,tblOperational[Planned_Visits]) -> 12888 | J11: =H11-I11 -> -4733 | K11: =H11/I11 -> 0.63275916 | L11: =AVERAGEIF(tblOperational[Rep_ID],A11,tblOperational[Merchandising_Compliance]) -> 0.555204 | M11: =L11-0.9 -> -0.344796 | N11: =AVERAGEIF(tblOperational[Rep_ID],A11,tblOperational[Product_Availability]) -> 0.562784 | O11: =N11-0.95 -> -0.387216 | P11: =IF(AND(G11>=0.9,L11>=0.8),"Healthy",IF(OR(G11<0.8,L11<0.7),"Critical","At Risk")) -> Critical
A12: =Raw_Reps!A35 -> 321830 | B12: =Raw_Reps!B35 -> Maren Musto | C12: =INDEX(tblRegions[name],MATCH(Raw_Reps!C35,tblRegions[id],0)) -> Southeast | D12: =SUMIF(tblOperational[Rep_ID],A12,tblOperational[Actual_Sales]) -> 173222.53 | E12: =SUMIF(tblOperational[Rep_ID],A12,tblOperational[Target]) -> 220091.53 | F12: =D12-E12 -> -46869.003 | G12: =IFERROR(D12/E12,0) -> 0.78704768 | H12: =SUMIF(tblOperational[Rep_ID],A12,tblOperational[Completed_Visits]) -> 8689 | I12: =SUMIF(tblOperational[Rep_ID],A12,tblOperational[Planned_Visits]) -> 13788 | J12: =H12-I12 -> -5099 | K12: =H12/I12 -> 0.63018567 | L12: =AVERAGEIF(tblOperational[Rep_ID],A12,tblOperational[Merchandising_Compliance]) -> 0.561256 | M12: =L12-0.9 -> -0.338744 | N12: =AVERAGEIF(tblOperational[Rep_ID],A12,tblOperational[Product_Availability]) -> 0.571856 | O12: =N12-0.95 -> -0.378144 | P12: =IF(AND(G12>=0.9,L12>=0.8),"Healthy",IF(OR(G12<0.8,L12<0.7),"Critical","At Risk")) -> Critical
A13: =Raw_Reps!A23 -> 321710 | B13: =Raw_Reps!B23 -> Sherlene Wetherington | C13: =INDEX(tblRegions[name],MATCH(Raw_Reps!C23,tblRegions[id],0)) -> Midwest | D13: =SUMIF(tblOperational[Rep_ID],A13,tblOperational[Actual_Sales]) -> 104177.49 | E13: =SUMIF(tblOperational[Rep_ID],A13,tblOperational[Target]) -> 137018.2 | F13: =D13-E13 -> -32840.714 | G13: =IFERROR(D13/E13,0) -> 0.76031861 | H13: =SUMIF(tblOperational[Rep_ID],A13,tblOperational[Completed_Visits]) -> 7908 | I13: =SUMIF(tblOperational[Rep_ID],A13,tblOperational[Planned_Visits]) -> 12288 | J13: =H13-I13 -> -4380 | K13: =H13/I13 -> 0.64355469 | L13: =AVERAGEIF(tblOperational[Rep_ID],A13,tblOperational[Merchandising_Compliance]) -> 0.589692 | M13: =L13-0.9 -> -0.310308 | N13: =AVERAGEIF(tblOperational[Rep_ID],A13,tblOperational[Product_Availability]) -> 0.607452 | O13: =N13-0.95 -> -0.342548 | P13: =IF(AND(G13>=0.9,L13>=0.8),"Healthy",IF(OR(G13<0.8,L13<0.7),"Critical","At Risk")) -> Critical
A14: =Raw_Reps!A30 -> 321780 | B14: =Raw_Reps!B30 -> Julie Starr | C14: =INDEX(tblRegions[name],MATCH(Raw_Reps!C30,tblRegions[id],0)) -> Midwest | D14: =SUMIF(tblOperational[Rep_ID],A14,tblOperational[Actual_Sales]) -> 24241.46 | E14: =SUMIF(tblOperational[Rep_ID],A14,tblOperational[Target]) -> 55048.411 | F14: =D14-E14 -> -30806.951 | G14: =IFERROR(D14/E14,0) -> 0.44036621 | H14: =SUMIF(tblOperational[Rep_ID],A14,tblOperational[Completed_Visits]) -> 10631 | I14: =SUMIF(tblOperational[Rep_ID],A14,tblOperational[Planned_Visits]) -> 12288 | J14: =H14-I14 -> -1657 | K14: =H14/I14 -> 0.86515299 | L14: =AVERAGEIF(tblOperational[Rep_ID],A14,tblOperational[Merchandising_Compliance]) -> 0.796268 | M14: =L14-0.9 -> -0.103732 | N14: =AVERAGEIF(tblOperational[Rep_ID],A14,tblOperational[Product_Availability]) -> 0.839784 | O14: =N14-0.95 -> -0.110216 | P14: =IF(AND(G14>=0.9,L14>=0.8),"Healthy",IF(OR(G14<0.8,L14<0.7),"Critical","At Risk")) -> Critical
A15: =Raw_Reps!A14 -> 321620 | B15: =Raw_Reps!B14 -> Retha Sears | C15: =INDEX(tblRegions[name],MATCH(Raw_Reps!C14,tblRegions[id],0)) -> Northeast | D15: =SUMIF(tblOperational[Rep_ID],A15,tblOperational[Actual_Sales]) -> 53699.03 | E15: =SUMIF(tblOperational[Rep_ID],A15,tblOperational[Target]) -> 81950.686 | F15: =D15-E15 -> -28251.656 | G15: =IFERROR(D15/E15,0) -> 0.65526028 | H15: =SUMIF(tblOperational[Rep_ID],A15,tblOperational[Completed_Visits]) -> 11009 | I15: =SUMIF(tblOperational[Rep_ID],A15,tblOperational[Planned_Visits]) -> 13788 | J15: =H15-I15 -> -2779 | K15: =H15/I15 -> 0.79844793 | L15: =AVERAGEIF(tblOperational[Rep_ID],A15,tblOperational[Merchandising_Compliance]) -> 0.730152 | M15: =L15-0.9 -> -0.169848 | N15: =AVERAGEIF(tblOperational[Rep_ID],A15,tblOperational[Product_Availability]) -> 0.76274 | O15: =N15-0.95 -> -0.18726 | P15: =IF(AND(G15>=0.9,L15>=0.8),"Healthy",IF(OR(G15<0.8,L15<0.7),"Critical","At Risk")) -> Critical
A16: =Raw_Reps!A49 -> 321970 | B16: =Raw_Reps!B49 -> Georgianna Chisholm | C16: =INDEX(tblRegions[name],MATCH(Raw_Reps!C49,tblRegions[id],0)) -> West | D16: =SUMIF(tblOperational[Rep_ID],A16,tblOperational[Actual_Sales]) -> 157954.71 | E16: =SUMIF(tblOperational[Rep_ID],A16,tblOperational[Target]) -> 177260.46 | F16: =D16-E16 -> -19305.751 | G16: =IFERROR(D16/E16,0) -> 0.89108823 | H16: =SUMIF(tblOperational[Rep_ID],A16,tblOperational[Completed_Visits]) -> 11055 | I16: =SUMIF(tblOperational[Rep_ID],A16,tblOperational[Planned_Visits]) -> 13788 | J16: =H16-I16 -> -2733 | K16: =H16/I16 -> 0.80178416 | L16: =AVERAGEIF(tblOperational[Rep_ID],A16,tblOperational[Merchandising_Compliance]) -> 0.765968 | M16: =L16-0.9 -> -0.134032 | N16: =AVERAGEIF(tblOperational[Rep_ID],A16,tblOperational[Product_Availability]) -> 0.794912 | O16: =N16-0.95 -> -0.155088 | P16: =IF(AND(G16>=0.9,L16>=0.8),"Healthy",IF(OR(G16<0.8,L16<0.7),"Critical","At Risk")) -> At Risk
A17: =Raw_Reps!A6 -> 321540 | B17: =Raw_Reps!B6 -> Cara Clarke | C17: =INDEX(tblRegions[name],MATCH(Raw_Reps!C6,tblRegions[id],0)) -> Northeast | D17: =SUMIF(tblOperational[Rep_ID],A17,tblOperational[Actual_Sales]) -> 55061.03 | E17: =SUMIF(tblOperational[Rep_ID],A17,tblOperational[Target]) -> 70483.008 | F17: =D17-E17 -> -15421.978 | G17: =IFERROR(D17/E17,0) -> 0.7811958 | H17: =SUMIF(tblOperational[Rep_ID],A17,tblOperational[Completed_Visits]) -> 7418 | I17: =SUMIF(tblOperational[Rep_ID],A17,tblOperational[Planned_Visits]) -> 13488 | J17: =H17-I17 -> -6070 | K17: =H17/I17 -> 0.54997034 | L17: =AVERAGEIF(tblOperational[Rep_ID],A17,tblOperational[Merchandising_Compliance]) -> 0.4 | M17: =L17-0.9 -> -0.5 | N17: =AVERAGEIF(tblOperational[Rep_ID],A17,tblOperational[Product_Availability]) -> 0.45 | O17: =N17-0.95 -> -0.5 | P17: =IF(AND(G17>=0.9,L17>=0.8),"Healthy",IF(OR(G17<0.8,L17<0.7),"Critical","At Risk")) -> Critical
A18: =Raw_Reps!A41 -> 321890 | B18: =Raw_Reps!B41 -> Nelle Meaux | C18: =INDEX(tblRegions[name],MATCH(Raw_Reps!C41,tblRegions[id],0)) -> Southeast | D18: =SUMIF(tblOperational[Rep_ID],A18,tblOperational[Actual_Sales]) -> 246219.24 | E18: =SUMIF(tblOperational[Rep_ID],A18,tblOperational[Target]) -> 261219.13 | F18: =D18-E18 -> -14999.889 | G18: =IFERROR(D18/E18,0) -> 0.94257737 | H18: =SUMIF(tblOperational[Rep_ID],A18,tblOperational[Completed_Visits]) -> 11988 | I18: =SUMIF(tblOperational[Rep_ID],A18,tblOperational[Planned_Visits]) -> 13488 | J18: =H18-I18 -> -1500 | K18: =H18/I18 -> 0.88879004 | L18: =AVERAGEIF(tblOperational[Rep_ID],A18,tblOperational[Merchandising_Compliance]) -> 0.857844 | M18: =L18-0.9 -> -0.042156 | N18: =AVERAGEIF(tblOperational[Rep_ID],A18,tblOperational[Product_Availability]) -> 0.892224 | O18: =N18-0.95 -> -0.057776 | P18: =IF(AND(G18>=0.9,L18>=0.8),"Healthy",IF(OR(G18<0.8,L18<0.7),"Critical","At Risk")) -> Healthy
A19: =Raw_Reps!A20 -> 321680 | B19: =Raw_Reps!B20 -> Elna Condello | C19: =INDEX(tblRegions[name],MATCH(Raw_Reps!C20,tblRegions[id],0)) -> Northeast | D19: =SUMIF(tblOperational[Rep_ID],A19,tblOperational[Actual_Sales]) -> 180058.73 | E19: =SUMIF(tblOperational[Rep_ID],A19,tblOperational[Target]) -> 192464.91 | F19: =D19-E19 -> -12406.176 | G19: =IFERROR(D19/E19,0) -> 0.93554058 | H19: =SUMIF(tblOperational[Rep_ID],A19,tblOperational[Completed_Visits]) -> 12369 | I19: =SUMIF(tblOperational[Rep_ID],A19,tblOperational[Planned_Visits]) -> 13488 | J19: =H19-I19 -> -1119 | K19: =H19/I19 -> 0.91703737 | L19: =AVERAGEIF(tblOperational[Rep_ID],A19,tblOperational[Merchandising_Compliance]) -> 0.882404 | M19: =L19-0.9 -> -0.017596 | N19: =AVERAGEIF(tblOperational[Rep_ID],A19,tblOperational[Product_Availability]) -> 0.93276 | O19: =N19-0.95 -> -0.01724 | P19: =IF(AND(G19>=0.9,L19>=0.8),"Healthy",IF(OR(G19<0.8,L19<0.7),"Critical","At Risk")) -> Healthy
A20: =Raw_Reps!A24 -> 321720 | B20: =Raw_Reps!B24 -> Chau Rowles | C20: =INDEX(tblRegions[name],MATCH(Raw_Reps!C24,tblRegions[id],0)) -> Midwest | D20: =SUMIF(tblOperational[Rep_ID],A20,tblOperational[Actual_Sales]) -> 60449.2 | E20: =SUMIF(tblOperational[Rep_ID],A20,tblOperational[Target]) -> 70720.486 | F20: =D20-E20 -> -10271.286 | G20: =IFERROR(D20/E20,0) -> 0.85476222 | H20: =SUMIF(tblOperational[Rep_ID],A20,tblOperational[Completed_Visits]) -> 12294 | I20: =SUMIF(tblOperational[Rep_ID],A20,tblOperational[Planned_Visits]) -> 12588 | J20: =H20-I20 -> -294 | K20: =H20/I20 -> 0.97664442 | L20: =AVERAGEIF(tblOperational[Rep_ID],A20,tblOperational[Merchandising_Compliance]) -> 0.956556 | M20: =L20-0.9 -> 0.056556 | N20: =AVERAGEIF(tblOperational[Rep_ID],A20,tblOperational[Product_Availability]) -> 0.975592 | O20: =N20-0.95 -> 0.025592 | P20: =IF(AND(G20>=0.9,L20>=0.8),"Healthy",IF(OR(G20<0.8,L20<0.7),"Critical","At Risk")) -> At Risk
A21: =Raw_Reps!A17 -> 321650 | B21: =Raw_Reps!B17 -> Akilah Drinkard | C21: =INDEX(tblRegions[name],MATCH(Raw_Reps!C17,tblRegions[id],0)) -> Northeast | D21: =SUMIF(tblOperational[Rep_ID],A21,tblOperational[Actual_Sales]) -> 83872.45 | E21: =SUMIF(tblOperational[Rep_ID],A21,tblOperational[Target]) -> 93989.759 | F21: =D21-E21 -> -10117.309 | G21: =IFERROR(D21/E21,0) -> 0.89235732 | H21: =SUMIF(tblOperational[Rep_ID],A21,tblOperational[Completed_Visits]) -> 7823 | I21: =SUMIF(tblOperational[Rep_ID],A21,tblOperational[Planned_Visits]) -> 12588 | J21: =H21-I21 -> -4765 | K21: =H21/I21 -> 0.62146489 | L21: =AVERAGEIF(tblOperational[Rep_ID],A21,tblOperational[Merchandising_Compliance]) -> 0.544456 | M21: =L21-0.9 -> -0.355544 | N21: =AVERAGEIF(tblOperational[Rep_ID],A21,tblOperational[Product_Availability]) -> 0.569136 | O21: =N21-0.95 -> -0.380864 | P21: =IF(AND(G21>=0.9,L21>=0.8),"Healthy",IF(OR(G21<0.8,L21<0.7),"Critical","At Risk")) -> Critical
A22: =Raw_Reps!A28 -> 321760 | B22: =Raw_Reps!B28 -> Delilah Krum | C22: =INDEX(tblRegions[name],MATCH(Raw_Reps!C28,tblRegions[id],0)) -> Midwest | D22: =SUMIF(tblOperational[Rep_ID],A22,tblOperational[Actual_Sales]) -> 223979.95 | E22: =SUMIF(tblOperational[Rep_ID],A22,tblOperational[Target]) -> 233909.45 | F22: =D22-E22 -> -9929.5004 | G22: =IFERROR(D22/E22,0) -> 0.95754981 | H22: =SUMIF(tblOperational[Rep_ID],A22,tblOperational[Completed_Visits]) -> 11902 | I22: =SUMIF(tblOperational[Rep_ID],A22,tblOperational[Planned_Visits]) -> 13788 | J22: =H22-I22 -> -1886 | K22: =H22/I22 -> 0.86321439 | L22: =AVERAGEIF(tblOperational[Rep_ID],A22,tblOperational[Merchandising_Compliance]) -> 0.835272 | M22: =L22-0.9 -> -0.064728 | N22: =AVERAGEIF(tblOperational[Rep_ID],A22,tblOperational[Product_Availability]) -> 0.855976 | O22: =N22-0.95 -> -0.094024 | P22: =IF(AND(G22>=0.9,L22>=0.8),"Healthy",IF(OR(G22<0.8,L22<0.7),"Critical","At Risk")) -> Healthy
A23: =Raw_Reps!A26 -> 321740 | B23: =Raw_Reps!B26 -> Charles Bidwell | C23: =INDEX(tblRegions[name],MATCH(Raw_Reps!C26,tblRegions[id],0)) -> Midwest | D23: =SUMIF(tblOperational[Rep_ID],A23,tblOperational[Actual_Sales]) -> 219821.47 | E23: =SUMIF(tblOperational[Rep_ID],A23,tblOperational[Target]) -> 228489.56 | F23: =D23-E23 -> -8668.0917 | G23: =IFERROR(D23/E23,0) -> 0.96206351 | H23: =SUMIF(tblOperational[Rep_ID],A23,tblOperational[Completed_Visits]) -> 9350 | I23: =SUMIF(tblOperational[Rep_ID],A23,tblOperational[Planned_Visits]) -> 13188 | J23: =H23-I23 -> -3838 | K23: =H23/I23 -> 0.70897786 | L23: =AVERAGEIF(tblOperational[Rep_ID],A23,tblOperational[Merchandising_Compliance]) -> 0.642748 | M23: =L23-0.9 -> -0.257252 | N23: =AVERAGEIF(tblOperational[Rep_ID],A23,tblOperational[Product_Availability]) -> 0.657548 | O23: =N23-0.95 -> -0.292452 | P23: =IF(AND(G23>=0.9,L23>=0.8),"Healthy",IF(OR(G23<0.8,L23<0.7),"Critical","At Risk")) -> Critical
A24: =Raw_Reps!A27 -> 321750 | B24: =Raw_Reps!B27 -> Cliff Meints | C24: =INDEX(tblRegions[name],MATCH(Raw_Reps!C27,tblRegions[id],0)) -> Midwest | D24: =SUMIF(tblOperational[Rep_ID],A24,tblOperational[Actual_Sales]) -> 236912.67 | E24: =SUMIF(tblOperational[Rep_ID],A24,tblOperational[Target]) -> 243989.93 | F24: =D24-E24 -> -7077.2553 | G24: =IFERROR(D24/E24,0) -> 0.97099366 | H24: =SUMIF(tblOperational[Rep_ID],A24,tblOperational[Completed_Visits]) -> 9912 | I24: =SUMIF(tblOperational[Rep_ID],A24,tblOperational[Planned_Visits]) -> 13488 | J24: =H24-I24 -> -3576 | K24: =H24/I24 -> 0.73487544 | L24: =AVERAGEIF(tblOperational[Rep_ID],A24,tblOperational[Merchandising_Compliance]) -> 0.649616 | M24: =L24-0.9 -> -0.250384 | N24: =AVERAGEIF(tblOperational[Rep_ID],A24,tblOperational[Product_Availability]) -> 0.678732 | O24: =N24-0.95 -> -0.271268 | P24: =IF(AND(G24>=0.9,L24>=0.8),"Healthy",IF(OR(G24<0.8,L24<0.7),"Critical","At Risk")) -> Critical
A25: =Raw_Reps!A7 -> 321550 | B25: =Raw_Reps!B7 -> Lavera Oles | C25: =INDEX(tblRegions[name],MATCH(Raw_Reps!C7,tblRegions[id],0)) -> Northeast | D25: =SUMIF(tblOperational[Rep_ID],A25,tblOperational[Actual_Sales]) -> 90920.19 | E25: =SUMIF(tblOperational[Rep_ID],A25,tblOperational[Target]) -> 96601.419 | F25: =D25-E25 -> -5681.2294 | G25: =IFERROR(D25/E25,0) -> 0.94118897 | H25: =SUMIF(tblOperational[Rep_ID],A25,tblOperational[Completed_Visits]) -> 7732 | I25: =SUMIF(tblOperational[Rep_ID],A25,tblOperational[Planned_Visits]) -> 13788 | J25: =H25-I25 -> -6056 | K25: =H25/I25 -> 0.56077749 | L25: =AVERAGEIF(tblOperational[Rep_ID],A25,tblOperational[Merchandising_Compliance]) -> 0.455752 | M25: =L25-0.9 -> -0.444248 | N25: =AVERAGEIF(tblOperational[Rep_ID],A25,tblOperational[Product_Availability]) -> 0.482704 | O25: =N25-0.95 -> -0.467296 | P25: =IF(AND(G25>=0.9,L25>=0.8),"Healthy",IF(OR(G25<0.8,L25<0.7),"Critical","At Risk")) -> Critical
A26: =Raw_Reps!A5 -> 321530 | B26: =Raw_Reps!B5 -> Renetta Carew | C26: =INDEX(tblRegions[name],MATCH(Raw_Reps!C5,tblRegions[id],0)) -> Northeast | D26: =SUMIF(tblOperational[Rep_ID],A26,tblOperational[Actual_Sales]) -> 78258.44 | E26: =SUMIF(tblOperational[Rep_ID],A26,tblOperational[Target]) -> 83596.353 | F26: =D26-E26 -> -5337.9132 | G26: =IFERROR(D26/E26,0) -> 0.93614658 | H26: =SUMIF(tblOperational[Rep_ID],A26,tblOperational[Completed_Visits]) -> 12505 | I26: =SUMIF(tblOperational[Rep_ID],A26,tblOperational[Planned_Visits]) -> 13188 | J26: =H26-I26 -> -683 | K26: =H26/I26 -> 0.94821049 | L26: =AVERAGEIF(tblOperational[Rep_ID],A26,tblOperational[Merchandising_Compliance]) -> 0.90224 | M26: =L26-0.9 -> 0.00224 | N26: =AVERAGEIF(tblOperational[Rep_ID],A26,tblOperational[Product_Availability]) -> 0.942612 | O26: =N26-0.95 -> -0.007388 | P26: =IF(AND(G26>=0.9,L26>=0.8),"Healthy",IF(OR(G26<0.8,L26<0.7),"Critical","At Risk")) -> Healthy
A27: =Raw_Reps!A8 -> 321560 | B27: =Raw_Reps!B8 -> Elba Felder | C27: =INDEX(tblRegions[name],MATCH(Raw_Reps!C8,tblRegions[id],0)) -> Northeast | D27: =SUMIF(tblOperational[Rep_ID],A27,tblOperational[Actual_Sales]) -> 29775.22 | E27: =SUMIF(tblOperational[Rep_ID],A27,tblOperational[Target]) -> 34173.693 | F27: =D27-E27 -> -4398.473 | G27: =IFERROR(D27/E27,0) -> 0.87129067 | H27: =SUMIF(tblOperational[Rep_ID],A27,tblOperational[Completed_Visits]) -> 11202 | I27: =SUMIF(tblOperational[Rep_ID],A27,tblOperational[Planned_Visits]) -> 14088 | J27: =H27-I27 -> -2886 | K27: =H27/I27 -> 0.7951448 | L27: =AVERAGEIF(tblOperational[Rep_ID],A27,tblOperational[Merchandising_Compliance]) -> 0.74272 | M27: =L27-0.9 -> -0.15728 | N27: =AVERAGEIF(tblOperational[Rep_ID],A27,tblOperational[Product_Availability]) -> 0.767744 | O27: =N27-0.95 -> -0.182256 | P27: =IF(AND(G27>=0.9,L27>=0.8),"Healthy",IF(OR(G27<0.8,L27<0.7),"Critical","At Risk")) -> At Risk
A28: =Raw_Reps!A33 -> 321810 | B28: =Raw_Reps!B33 -> Moon Torian | C28: =INDEX(tblRegions[name],MATCH(Raw_Reps!C33,tblRegions[id],0)) -> Southeast | D28: =SUMIF(tblOperational[Rep_ID],A28,tblOperational[Actual_Sales]) -> 341111.93 | E28: =SUMIF(tblOperational[Rep_ID],A28,tblOperational[Target]) -> 343670.09 | F28: =D28-E28 -> -2558.1585 | G28: =IFERROR(D28/E28,0) -> 0.99255635 | H28: =SUMIF(tblOperational[Rep_ID],A28,tblOperational[Completed_Visits]) -> 9267 | I28: =SUMIF(tblOperational[Rep_ID],A28,tblOperational[Planned_Visits]) -> 13188 | J28: =H28-I28 -> -3921 | K28: =H28/I28 -> 0.70268426 | L28: =AVERAGEIF(tblOperational[Rep_ID],A28,tblOperational[Merchandising_Compliance]) -> 0.647812 | M28: =L28-0.9 -> -0.252188 | N28: =AVERAGEIF(tblOperational[Rep_ID],A28,tblOperational[Product_Availability]) -> 0.657172 | O28: =N28-0.95 -> -0.292828 | P28: =IF(AND(G28>=0.9,L28>=0.8),"Healthy",IF(OR(G28<0.8,L28<0.7),"Critical","At Risk")) -> Critical
A29: =Raw_Reps!A15 -> 321630 | B29: =Raw_Reps!B15 -> Julia Behrman | C29: =INDEX(tblRegions[name],MATCH(Raw_Reps!C15,tblRegions[id],0)) -> Northeast | D29: =SUMIF(tblOperational[Rep_ID],A29,tblOperational[Actual_Sales]) -> 193679.37 | E29: =SUMIF(tblOperational[Rep_ID],A29,tblOperational[Target]) -> 192371.74 | F29: =D29-E29 -> 1307.6303 | G29: =IFERROR(D29/E29,0) -> 1.0067974 | H29: =SUMIF(tblOperational[Rep_ID],A29,tblOperational[Completed_Visits]) -> 13790 | I29: =SUMIF(tblOperational[Rep_ID],A29,tblOperational[Planned_Visits]) -> 14088 | J29: =H29-I29 -> -298 | K29: =H29/I29 -> 0.97884725 | L29: =AVERAGEIF(tblOperational[Rep_ID],A29,tblOperational[Merchandising_Compliance]) -> 0.939876 | M29: =L29-0.9 -> 0.039876 | N29: =AVERAGEIF(tblOperational[Rep_ID],A29,tblOperational[Product_Availability]) -> 0.965184 | O29: =N29-0.95 -> 0.015184 | P29: =IF(AND(G29>=0.9,L29>=0.8),"Healthy",IF(OR(G29<0.8,L29<0.7),"Critical","At Risk")) -> Healthy
A30: =Raw_Reps!A31 -> 321790 | B30: =Raw_Reps!B31 -> Cordell Rieder | C30: =INDEX(tblRegions[name],MATCH(Raw_Reps!C31,tblRegions[id],0)) -> Midwest | D30: =SUMIF(tblOperational[Rep_ID],A30,tblOperational[Actual_Sales]) -> 84700.04 | E30: =SUMIF(tblOperational[Rep_ID],A30,tblOperational[Target]) -> 82808.219 | F30: =D30-E30 -> 1891.8209 | G30: =IFERROR(D30/E30,0) -> 1.0228458 | H30: =SUMIF(tblOperational[Rep_ID],A30,tblOperational[Completed_Visits]) -> 10806 | I30: =SUMIF(tblOperational[Rep_ID],A30,tblOperational[Planned_Visits]) -> 12588 | J30: =H30-I30 -> -1782 | K30: =H30/I30 -> 0.85843661 | L30: =AVERAGEIF(tblOperational[Rep_ID],A30,tblOperational[Merchandising_Compliance]) -> 0.80118 | M30: =L30-0.9 -> -0.09882 | N30: =AVERAGEIF(tblOperational[Rep_ID],A30,tblOperational[Product_Availability]) -> 0.850296 | O30: =N30-0.95 -> -0.099704 | P30: =IF(AND(G30>=0.9,L30>=0.8),"Healthy",IF(OR(G30<0.8,L30<0.7),"Critical","At Risk")) -> Healthy
A31: =Raw_Reps!A38 -> 321860 | B31: =Raw_Reps!B38 -> Saran Ram | C31: =INDEX(tblRegions[name],MATCH(Raw_Reps!C38,tblRegions[id],0)) -> Southeast | D31: =SUMIF(tblOperational[Rep_ID],A31,tblOperational[Actual_Sales]) -> 157220.51 | E31: =SUMIF(tblOperational[Rep_ID],A31,tblOperational[Target]) -> 155267.71 | F31: =D31-E31 -> 1952.801 | G31: =IFERROR(D31/E31,0) -> 1.012577 | H31: =SUMIF(tblOperational[Rep_ID],A31,tblOperational[Completed_Visits]) -> 9624 | I31: =SUMIF(tblOperational[Rep_ID],A31,tblOperational[Planned_Visits]) -> 12588 | J31: =H31-I31 -> -2964 | K31: =H31/I31 -> 0.76453765 | L31: =AVERAGEIF(tblOperational[Rep_ID],A31,tblOperational[Merchandising_Compliance]) -> 0.69802 | M31: =L31-0.9 -> -0.20198 | N31: =AVERAGEIF(tblOperational[Rep_ID],A31,tblOperational[Product_Availability]) -> 0.731456 | O31: =N31-0.95 -> -0.218544 | P31: =IF(AND(G31>=0.9,L31>=0.8),"Healthy",IF(OR(G31<0.8,L31<0.7),"Critical","At Risk")) -> Critical
A32: =Raw_Reps!A50 -> 321980 | B32: =Raw_Reps!B50 -> Micha Woodford | C32: =INDEX(tblRegions[name],MATCH(Raw_Reps!C50,tblRegions[id],0)) -> West | D32: =SUMIF(tblOperational[Rep_ID],A32,tblOperational[Actual_Sales]) -> 221862.21 | E32: =SUMIF(tblOperational[Rep_ID],A32,tblOperational[Target]) -> 219888.29 | F32: =D32-E32 -> 1973.9228 | G32: =IFERROR(D32/E32,0) -> 1.0089769 | H32: =SUMIF(tblOperational[Rep_ID],A32,tblOperational[Completed_Visits]) -> 12613 | I32: =SUMIF(tblOperational[Rep_ID],A32,tblOperational[Planned_Visits]) -> 14088 | J32: =H32-I32 -> -1475 | K32: =H32/I32 -> 0.89530097 | L32: =AVERAGEIF(tblOperational[Rep_ID],A32,tblOperational[Merchandising_Compliance]) -> 0.854584 | M32: =L32-0.9 -> -0.045416 | N32: =AVERAGEIF(tblOperational[Rep_ID],A32,tblOperational[Product_Availability]) -> 0.897196 | O32: =N32-0.95 -> -0.052804 | P32: =IF(AND(G32>=0.9,L32>=0.8),"Healthy",IF(OR(G32<0.8,L32<0.7),"Critical","At Risk")) -> Healthy
A33: =Raw_Reps!A43 -> 321910 | B33: =Raw_Reps!B43 -> Brandie Riva | C33: =INDEX(tblRegions[name],MATCH(Raw_Reps!C43,tblRegions[id],0)) -> West | D33: =SUMIF(tblOperational[Rep_ID],A33,tblOperational[Actual_Sales]) -> 198796.33 | E33: =SUMIF(tblOperational[Rep_ID],A33,tblOperational[Target]) -> 195449.08 | F33: =D33-E33 -> 3347.2542 | G33: =IFERROR(D33/E33,0) -> 1.017126 | H33: =SUMIF(tblOperational[Rep_ID],A33,tblOperational[Completed_Visits]) -> 12529 | I33: =SUMIF(tblOperational[Rep_ID],A33,tblOperational[Planned_Visits]) -> 14088 | J33: =H33-I33 -> -1559 | K33: =H33/I33 -> 0.88933844 | L33: =AVERAGEIF(tblOperational[Rep_ID],A33,tblOperational[Merchandising_Compliance]) -> 0.833496 | M33: =L33-0.9 -> -0.066504 | N33: =AVERAGEIF(tblOperational[Rep_ID],A33,tblOperational[Product_Availability]) -> 0.866696 | O33: =N33-0.95 -> -0.083304 | P33: =IF(AND(G33>=0.9,L33>=0.8),"Healthy",IF(OR(G33<0.8,L33<0.7),"Critical","At Risk")) -> Healthy
A34: =Raw_Reps!A32 -> 321800 | B34: =Raw_Reps!B32 -> Earlie Schleusner | C34: =INDEX(tblRegions[name],MATCH(Raw_Reps!C32,tblRegions[id],0)) -> Southeast | D34: =SUMIF(tblOperational[Rep_ID],A34,tblOperational[Actual_Sales]) -> 370640.45 | E34: =SUMIF(tblOperational[Rep_ID],A34,tblOperational[Target]) -> 365725.32 | F34: =D34-E34 -> 4915.133 | G34: =IFERROR(D34/E34,0) -> 1.0134394 | H34: =SUMIF(tblOperational[Rep_ID],A34,tblOperational[Completed_Visits]) -> 12763 | I34: =SUMIF(tblOperational[Rep_ID],A34,tblOperational[Planned_Visits]) -> 12888 | J34: =H34-I34 -> -125 | K34: =H34/I34 -> 0.99030106 | L34: =AVERAGEIF(tblOperational[Rep_ID],A34,tblOperational[Merchandising_Compliance]) -> 0.97 | M34: =L34-0.9 -> 0.07 | N34: =AVERAGEIF(tblOperational[Rep_ID],A34,tblOperational[Product_Availability]) -> 0.98 | O34: =N34-0.95 -> 0.03 | P34: =IF(AND(G34>=0.9,L34>=0.8),"Healthy",IF(OR(G34<0.8,L34<0.7),"Critical","At Risk")) -> Healthy
A35: =Raw_Reps!A13 -> 321610 | B35: =Raw_Reps!B13 -> Ayesha Monica | C35: =INDEX(tblRegions[name],MATCH(Raw_Reps!C13,tblRegions[id],0)) -> Northeast | D35: =SUMIF(tblOperational[Rep_ID],A35,tblOperational[Actual_Sales]) -> 111051.82 | E35: =SUMIF(tblOperational[Rep_ID],A35,tblOperational[Target]) -> 105856.31 | F35: =D35-E35 -> 5195.509 | G35: =IFERROR(D35/E35,0) -> 1.0490808 | H35: =SUMIF(tblOperational[Rep_ID],A35,tblOperational[Completed_Visits]) -> 12312 | I35: =SUMIF(tblOperational[Rep_ID],A35,tblOperational[Planned_Visits]) -> 13488 | J35: =H35-I35 -> -1176 | K35: =H35/I35 -> 0.91281139 | L35: =AVERAGEIF(tblOperational[Rep_ID],A35,tblOperational[Merchandising_Compliance]) -> 0.866496 | M35: =L35-0.9 -> -0.033504 | N35: =AVERAGEIF(tblOperational[Rep_ID],A35,tblOperational[Product_Availability]) -> 0.904064 | O35: =N35-0.95 -> -0.045936 | P35: =IF(AND(G35>=0.9,L35>=0.8),"Healthy",IF(OR(G35<0.8,L35<0.7),"Critical","At Risk")) -> Healthy
A36: =Raw_Reps!A9 -> 321570 | B36: =Raw_Reps!B9 -> Shawanda Selke | C36: =INDEX(tblRegions[name],MATCH(Raw_Reps!C9,tblRegions[id],0)) -> Northeast | D36: =SUMIF(tblOperational[Rep_ID],A36,tblOperational[Actual_Sales]) -> 153278.4 | E36: =SUMIF(tblOperational[Rep_ID],A36,tblOperational[Target]) -> 147973.64 | F36: =D36-E36 -> 5304.7574 | G36: =IFERROR(D36/E36,0) -> 1.0358493 | H36: =SUMIF(tblOperational[Rep_ID],A36,tblOperational[Completed_Visits]) -> 8833 | I36: =SUMIF(tblOperational[Rep_ID],A36,tblOperational[Planned_Visits]) -> 12288 | J36: =H36-I36 -> -3455 | K36: =H36/I36 -> 0.71883138 | L36: =AVERAGEIF(tblOperational[Rep_ID],A36,tblOperational[Merchandising_Compliance]) -> 0.652052 | M36: =L36-0.9 -> -0.247948 | N36: =AVERAGEIF(tblOperational[Rep_ID],A36,tblOperational[Product_Availability]) -> 0.693856 | O36: =N36-0.95 -> -0.256144 | P36: =IF(AND(G36>=0.9,L36>=0.8),"Healthy",IF(OR(G36<0.8,L36<0.7),"Critical","At Risk")) -> Critical
A37: =Raw_Reps!A21 -> 321690 | B37: =Raw_Reps!B21 -> Gianna Dossey | C37: =INDEX(tblRegions[name],MATCH(Raw_Reps!C21,tblRegions[id],0)) -> Northeast | D37: =SUMIF(tblOperational[Rep_ID],A37,tblOperational[Actual_Sales]) -> 200272.97 | E37: =SUMIF(tblOperational[Rep_ID],A37,tblOperational[Target]) -> 192241.54 | F37: =D37-E37 -> 8031.4278 | G37: =IFERROR(D37/E37,0) -> 1.0417778 | H37: =SUMIF(tblOperational[Rep_ID],A37,tblOperational[Completed_Visits]) -> 10644 | I37: =SUMIF(tblOperational[Rep_ID],A37,tblOperational[Planned_Visits]) -> 13788 | J37: =H37-I37 -> -3144 | K37: =H37/I37 -> 0.77197563 | L37: =AVERAGEIF(tblOperational[Rep_ID],A37,tblOperational[Merchandising_Compliance]) -> 0.701812 | M37: =L37-0.9 -> -0.198188 | N37: =AVERAGEIF(tblOperational[Rep_ID],A37,tblOperational[Product_Availability]) -> 0.732932 | O37: =N37-0.95 -> -0.217068 | P37: =IF(AND(G37>=0.9,L37>=0.8),"Healthy",IF(OR(G37<0.8,L37<0.7),"Critical","At Risk")) -> At Risk
A38: =Raw_Reps!A2 -> 321500 | B38: =Raw_Reps!B2 -> Samuel Racine | C38: =INDEX(tblRegions[name],MATCH(Raw_Reps!C2,tblRegions[id],0)) -> Northeast | D38: =SUMIF(tblOperational[Rep_ID],A38,tblOperational[Actual_Sales]) -> 133867.33 | E38: =SUMIF(tblOperational[Rep_ID],A38,tblOperational[Target]) -> 119437.17 | F38: =D38-E38 -> 14430.157 | G38: =IFERROR(D38/E38,0) -> 1.120818 | H38: =SUMIF(tblOperational[Rep_ID],A38,tblOperational[Completed_Visits]) -> 10227 | I38: =SUMIF(tblOperational[Rep_ID],A38,tblOperational[Planned_Visits]) -> 12288 | J38: =H38-I38 -> -2061 | K38: =H38/I38 -> 0.83227539 | L38: =AVERAGEIF(tblOperational[Rep_ID],A38,tblOperational[Merchandising_Compliance]) -> 0.773604 | M38: =L38-0.9 -> -0.126396 | N38: =AVERAGEIF(tblOperational[Rep_ID],A38,tblOperational[Product_Availability]) -> 0.810392 | O38: =N38-0.95 -> -0.139608 | P38: =IF(AND(G38>=0.9,L38>=0.8),"Healthy",IF(OR(G38<0.8,L38<0.7),"Critical","At Risk")) -> At Risk
A39: =Raw_Reps!A16 -> 321640 | B39: =Raw_Reps!B16 -> Tia Amato | C39: =INDEX(tblRegions[name],MATCH(Raw_Reps!C16,tblRegions[id],0)) -> Northeast | D39: =SUMIF(tblOperational[Rep_ID],A39,tblOperational[Actual_Sales]) -> 363628.01 | E39: =SUMIF(tblOperational[Rep_ID],A39,tblOperational[Target]) -> 347014.15 | F39: =D39-E39 -> 16613.857 | G39: =IFERROR(D39/E39,0) -> 1.0478766 | H39: =SUMIF(tblOperational[Rep_ID],A39,tblOperational[Completed_Visits]) -> 10580 | I39: =SUMIF(tblOperational[Rep_ID],A39,tblOperational[Planned_Visits]) -> 12288 | J39: =H39-I39 -> -1708 | K39: =H39/I39 -> 0.8610026 | L39: =AVERAGEIF(tblOperational[Rep_ID],A39,tblOperational[Merchandising_Compliance]) -> 0.823324 | M39: =L39-0.9 -> -0.076676 | N39: =AVERAGEIF(tblOperational[Rep_ID],A39,tblOperational[Product_Availability]) -> 0.832368 | O39: =N39-0.95 -> -0.117632 | P39: =IF(AND(G39>=0.9,L39>=0.8),"Healthy",IF(OR(G39<0.8,L39<0.7),"Critical","At Risk")) -> Healthy
A40: =Raw_Reps!A10 -> 321580 | B40: =Raw_Reps!B10 -> Sibyl Lauria | C40: =INDEX(tblRegions[name],MATCH(Raw_Reps!C10,tblRegions[id],0)) -> Northeast | D40: =SUMIF(tblOperational[Rep_ID],A40,tblOperational[Actual_Sales]) -> 218417.18 | E40: =SUMIF(tblOperational[Rep_ID],A40,tblOperational[Target]) -> 199912.81 | F40: =D40-E40 -> 18504.365 | G40: =IFERROR(D40/E40,0) -> 1.0925622 | H40: =SUMIF(tblOperational[Rep_ID],A40,tblOperational[Completed_Visits]) -> 9667 | I40: =SUMIF(tblOperational[Rep_ID],A40,tblOperational[Planned_Visits]) -> 12588 | J40: =H40-I40 -> -2921 | K40: =H40/I40 -> 0.76795361 | L40: =AVERAGEIF(tblOperational[Rep_ID],A40,tblOperational[Merchandising_Compliance]) -> 0.712796 | M40: =L40-0.9 -> -0.187204 | N40: =AVERAGEIF(tblOperational[Rep_ID],A40,tblOperational[Product_Availability]) -> 0.744316 | O40: =N40-0.95 -> -0.205684 | P40: =IF(AND(G40>=0.9,L40>=0.8),"Healthy",IF(OR(G40<0.8,L40<0.7),"Critical","At Risk")) -> At Risk
A41: =Raw_Reps!A22 -> 321700 | B41: =Raw_Reps!B22 -> Debroah Wardle | C41: =INDEX(tblRegions[name],MATCH(Raw_Reps!C22,tblRegions[id],0)) -> Northeast | D41: =SUMIF(tblOperational[Rep_ID],A41,tblOperational[Actual_Sales]) -> 188001.04 | E41: =SUMIF(tblOperational[Rep_ID],A41,tblOperational[Target]) -> 169474.41 | F41: =D41-E41 -> 18526.628 | G41: =IFERROR(D41/E41,0) -> 1.1093181 | H41: =SUMIF(tblOperational[Rep_ID],A41,tblOperational[Completed_Visits]) -> 10573 | I41: =SUMIF(tblOperational[Rep_ID],A41,tblOperational[Planned_Visits]) -> 14088 | J41: =H41-I41 -> -3515 | K41: =H41/I41 -> 0.75049688 | L41: =AVERAGEIF(tblOperational[Rep_ID],A41,tblOperational[Merchandising_Compliance]) -> 0.681656 | M41: =L41-0.9 -> -0.218344 | N41: =AVERAGEIF(tblOperational[Rep_ID],A41,tblOperational[Product_Availability]) -> 0.71616 | O41: =N41-0.95 -> -0.23384 | P41: =IF(AND(G41>=0.9,L41>=0.8),"Healthy",IF(OR(G41<0.8,L41<0.7),"Critical","At Risk")) -> Critical
A42: =Raw_Reps!A3 -> 321510 | B42: =Raw_Reps!B3 -> Eugena Esser | C42: =INDEX(tblRegions[name],MATCH(Raw_Reps!C3,tblRegions[id],0)) -> Northeast | D42: =SUMIF(tblOperational[Rep_ID],A42,tblOperational[Actual_Sales]) -> 116383.07 | E42: =SUMIF(tblOperational[Rep_ID],A42,tblOperational[Target]) -> 97530.572 | F42: =D42-E42 -> 18852.498 | G42: =IFERROR(D42/E42,0) -> 1.1932983 | H42: =SUMIF(tblOperational[Rep_ID],A42,tblOperational[Completed_Visits]) -> 7406 | I42: =SUMIF(tblOperational[Rep_ID],A42,tblOperational[Planned_Visits]) -> 12588 | J42: =H42-I42 -> -5182 | K42: =H42/I42 -> 0.5883381 | L42: =AVERAGEIF(tblOperational[Rep_ID],A42,tblOperational[Merchandising_Compliance]) -> 0.510936 | M42: =L42-0.9 -> -0.389064 | N42: =AVERAGEIF(tblOperational[Rep_ID],A42,tblOperational[Product_Availability]) -> 0.535344 | O42: =N42-0.95 -> -0.414656 | P42: =IF(AND(G42>=0.9,L42>=0.8),"Healthy",IF(OR(G42<0.8,L42<0.7),"Critical","At Risk")) -> Critical
A43: =Raw_Reps!A12 -> 321600 | B43: =Raw_Reps!B12 -> Ernestine Pickron | C43: =INDEX(tblRegions[name],MATCH(Raw_Reps!C12,tblRegions[id],0)) -> Northeast | D43: =SUMIF(tblOperational[Rep_ID],A43,tblOperational[Actual_Sales]) -> 183047.14 | E43: =SUMIF(tblOperational[Rep_ID],A43,tblOperational[Target]) -> 160479.28 | F43: =D43-E43 -> 22567.856 | G43: =IFERROR(D43/E43,0) -> 1.1406278 | H43: =SUMIF(tblOperational[Rep_ID],A43,tblOperational[Completed_Visits]) -> 12436 | I43: =SUMIF(tblOperational[Rep_ID],A43,tblOperational[Planned_Visits]) -> 13188 | J43: =H43-I43 -> -752 | K43: =H43/I43 -> 0.94297847 | L43: =AVERAGEIF(tblOperational[Rep_ID],A43,tblOperational[Merchandising_Compliance]) -> 0.908256 | M43: =L43-0.9 -> 0.008256 | N43: =AVERAGEIF(tblOperational[Rep_ID],A43,tblOperational[Product_Availability]) -> 0.939648 | O43: =N43-0.95 -> -0.010352 | P43: =IF(AND(G43>=0.9,L43>=0.8),"Healthy",IF(OR(G43<0.8,L43<0.7),"Critical","At Risk")) -> Healthy
A44: =Raw_Reps!A37 -> 321850 | B44: =Raw_Reps!B37 -> Calvin Ollison | C44: =INDEX(tblRegions[name],MATCH(Raw_Reps!C37,tblRegions[id],0)) -> Southeast | D44: =SUMIF(tblOperational[Rep_ID],A44,tblOperational[Actual_Sales]) -> 196348.27 | E44: =SUMIF(tblOperational[Rep_ID],A44,tblOperational[Target]) -> 169813.9 | F44: =D44-E44 -> 26534.365 | G44: =IFERROR(D44/E44,0) -> 1.1562556 | H44: =SUMIF(tblOperational[Rep_ID],A44,tblOperational[Completed_Visits]) -> 11866 | I44: =SUMIF(tblOperational[Rep_ID],A44,tblOperational[Planned_Visits]) -> 12288 | J44: =H44-I44 -> -422 | K44: =H44/I44 -> 0.96565755 | L44: =AVERAGEIF(tblOperational[Rep_ID],A44,tblOperational[Merchandising_Compliance]) -> 0.951312 | M44: =L44-0.9 -> 0.051312 | N44: =AVERAGEIF(tblOperational[Rep_ID],A44,tblOperational[Product_Availability]) -> 0.97334 | O44: =N44-0.95 -> 0.02334 | P44: =IF(AND(G44>=0.9,L44>=0.8),"Healthy",IF(OR(G44<0.8,L44<0.7),"Critical","At Risk")) -> Healthy
A45: =Raw_Reps!A4 -> 321520 | B45: =Raw_Reps!B4 -> Michel Averette | C45: =INDEX(tblRegions[name],MATCH(Raw_Reps!C4,tblRegions[id],0)) -> Northeast | D45: =SUMIF(tblOperational[Rep_ID],A45,tblOperational[Actual_Sales]) -> 209084.08 | E45: =SUMIF(tblOperational[Rep_ID],A45,tblOperational[Target]) -> 177414.27 | F45: =D45-E45 -> 31669.805 | G45: =IFERROR(D45/E45,0) -> 1.1785077 | H45: =SUMIF(tblOperational[Rep_ID],A45,tblOperational[Completed_Visits]) -> 11861 | I45: =SUMIF(tblOperational[Rep_ID],A45,tblOperational[Planned_Visits]) -> 12888 | J45: =H45-I45 -> -1027 | K45: =H45/I45 -> 0.92031347 | L45: =AVERAGEIF(tblOperational[Rep_ID],A45,tblOperational[Merchandising_Compliance]) -> 0.876112 | M45: =L45-0.9 -> -0.023888 | N45: =AVERAGEIF(tblOperational[Rep_ID],A45,tblOperational[Product_Availability]) -> 0.89872 | O45: =N45-0.95 -> -0.05128 | P45: =IF(AND(G45>=0.9,L45>=0.8),"Healthy",IF(OR(G45<0.8,L45<0.7),"Critical","At Risk")) -> Healthy
A46: =Raw_Reps!A34 -> 321820 | B46: =Raw_Reps!B34 -> Dorotha Seawell | C46: =INDEX(tblRegions[name],MATCH(Raw_Reps!C34,tblRegions[id],0)) -> Southeast | D46: =SUMIF(tblOperational[Rep_ID],A46,tblOperational[Actual_Sales]) -> 249802.23 | E46: =SUMIF(tblOperational[Rep_ID],A46,tblOperational[Target]) -> 214607.07 | F46: =D46-E46 -> 35195.158 | G46: =IFERROR(D46/E46,0) -> 1.1639981 | H46: =SUMIF(tblOperational[Rep_ID],A46,tblOperational[Completed_Visits]) -> 9426 | I46: =SUMIF(tblOperational[Rep_ID],A46,tblOperational[Planned_Visits]) -> 13488 | J46: =H46-I46 -> -4062 | K46: =H46/I46 -> 0.69884342 | L46: =AVERAGEIF(tblOperational[Rep_ID],A46,tblOperational[Merchandising_Compliance]) -> 0.61208 | M46: =L46-0.9 -> -0.28792 | N46: =AVERAGEIF(tblOperational[Rep_ID],A46,tblOperational[Product_Availability]) -> 0.64282 | O46: =N46-0.95 -> -0.30718 | P46: =IF(AND(G46>=0.9,L46>=0.8),"Healthy",IF(OR(G46<0.8,L46<0.7),"Critical","At Risk")) -> Critical
A47: =Raw_Reps!A11 -> 321590 | B47: =Raw_Reps!B11 -> Necole Victory | C47: =INDEX(tblRegions[name],MATCH(Raw_Reps!C11,tblRegions[id],0)) -> Northeast | D47: =SUMIF(tblOperational[Rep_ID],A47,tblOperational[Actual_Sales]) -> 215628.84 | E47: =SUMIF(tblOperational[Rep_ID],A47,tblOperational[Target]) -> 176020.99 | F47: =D47-E47 -> 39607.853 | G47: =IFERROR(D47/E47,0) -> 1.2250178 | H47: =SUMIF(tblOperational[Rep_ID],A47,tblOperational[Completed_Visits]) -> 8239 | I47: =SUMIF(tblOperational[Rep_ID],A47,tblOperational[Planned_Visits]) -> 12888 | J47: =H47-I47 -> -4649 | K47: =H47/I47 -> 0.63927685 | L47: =AVERAGEIF(tblOperational[Rep_ID],A47,tblOperational[Merchandising_Compliance]) -> 0.553892 | M47: =L47-0.9 -> -0.346108 | N47: =AVERAGEIF(tblOperational[Rep_ID],A47,tblOperational[Product_Availability]) -> 0.571072 | O47: =N47-0.95 -> -0.378928 | P47: =IF(AND(G47>=0.9,L47>=0.8),"Healthy",IF(OR(G47<0.8,L47<0.7),"Critical","At Risk")) -> Critical
A48: =Raw_Reps!A36 -> 321840 | B48: =Raw_Reps!B36 -> Vernita Plump | C48: =INDEX(tblRegions[name],MATCH(Raw_Reps!C36,tblRegions[id],0)) -> Southeast | D48: =SUMIF(tblOperational[Rep_ID],A48,tblOperational[Actual_Sales]) -> 399664.35 | E48: =SUMIF(tblOperational[Rep_ID],A48,tblOperational[Target]) -> 350460.89 | F48: =D48-E48 -> 49203.456 | G48: =IFERROR(D48/E48,0) -> 1.1403964 | H48: =SUMIF(tblOperational[Rep_ID],A48,tblOperational[Completed_Visits]) -> 12398 | I48: =SUMIF(tblOperational[Rep_ID],A48,tblOperational[Planned_Visits]) -> 14088 | J48: =H48-I48 -> -1690 | K48: =H48/I48 -> 0.88003975 | L48: =AVERAGEIF(tblOperational[Rep_ID],A48,tblOperational[Merchandising_Compliance]) -> 0.847148 | M48: =L48-0.9 -> -0.052852 | N48: =AVERAGEIF(tblOperational[Rep_ID],A48,tblOperational[Product_Availability]) -> 0.89322 | O48: =N48-0.95 -> -0.05678 | P48: =IF(AND(G48>=0.9,L48>=0.8),"Healthy",IF(OR(G48<0.8,L48<0.7),"Critical","At Risk")) -> Healthy
A49: =Raw_Reps!A46 -> 321940 | B49: =Raw_Reps!B46 -> Arica Stoltzfus | C49: =INDEX(tblRegions[name],MATCH(Raw_Reps!C46,tblRegions[id],0)) -> West | D49: =SUMIF(tblOperational[Rep_ID],A49,tblOperational[Actual_Sales]) -> 232133.62 | E49: =SUMIF(tblOperational[Rep_ID],A49,tblOperational[Target]) -> 177516.78 | F49: =D49-E49 -> 54616.838 | G49: =IFERROR(D49/E49,0) -> 1.3076714 | H49: =SUMIF(tblOperational[Rep_ID],A49,tblOperational[Completed_Visits]) -> 10299 | I49: =SUMIF(tblOperational[Rep_ID],A49,tblOperational[Planned_Visits]) -> 12888 | J49: =H49-I49 -> -2589 | K49: =H49/I49 -> 0.79911546 | L49: =AVERAGEIF(tblOperational[Rep_ID],A49,tblOperational[Merchandising_Compliance]) -> 0.7493 | M49: =L49-0.9 -> -0.1507 | N49: =AVERAGEIF(tblOperational[Rep_ID],A49,tblOperational[Product_Availability]) -> 0.771588 | O49: =N49-0.95 -> -0.178412 | P49: =IF(AND(G49>=0.9,L49>=0.8),"Healthy",IF(OR(G49<0.8,L49<0.7),"Critical","At Risk")) -> At Risk
A50: =Raw_Reps!A48 -> 321960 | B50: =Raw_Reps!B48 -> Maryanna Fiorentino | C50: =INDEX(tblRegions[name],MATCH(Raw_Reps!C48,tblRegions[id],0)) -> West | D50: =SUMIF(tblOperational[Rep_ID],A50,tblOperational[Actual_Sales]) -> 323739.6 | E50: =SUMIF(tblOperational[Rep_ID],A50,tblOperational[Target]) -> 263916.38 | F50: =D50-E50 -> 59823.22 | G50: =IFERROR(D50/E50,0) -> 1.2266749 | H50: =SUMIF(tblOperational[Rep_ID],A50,tblOperational[Completed_Visits]) -> 12552 | I50: =SUMIF(tblOperational[Rep_ID],A50,tblOperational[Planned_Visits]) -> 13488 | J50: =H50-I50 -> -936 | K50: =H50/I50 -> 0.93060498 | L50: =AVERAGEIF(tblOperational[Rep_ID],A50,tblOperational[Merchandising_Compliance]) -> 0.901332 | M50: =L50-0.9 -> 0.001332 | N50: =AVERAGEIF(tblOperational[Rep_ID],A50,tblOperational[Product_Availability]) -> 0.926524 | O50: =N50-0.95 -> -0.023476 | P50: =IF(AND(G50>=0.9,L50>=0.8),"Healthy",IF(OR(G50<0.8,L50<0.7),"Critical","At Risk")) -> Healthy
A51: =Raw_Reps!A47 -> 321950 | B51: =Raw_Reps!B47 -> Elwood Shutt | C51: =INDEX(tblRegions[name],MATCH(Raw_Reps!C47,tblRegions[id],0)) -> West | D51: =SUMIF(tblOperational[Rep_ID],A51,tblOperational[Actual_Sales]) -> 322766.89 | E51: =SUMIF(tblOperational[Rep_ID],A51,tblOperational[Target]) -> 257399.88 | F51: =D51-E51 -> 65367.013 | G51: =IFERROR(D51/E51,0) -> 1.2539512 | H51: =SUMIF(tblOperational[Rep_ID],A51,tblOperational[Completed_Visits]) -> 11082 | I51: =SUMIF(tblOperational[Rep_ID],A51,tblOperational[Planned_Visits]) -> 13188 | J51: =H51-I51 -> -2106 | K51: =H51/I51 -> 0.84030937 | L51: =AVERAGEIF(tblOperational[Rep_ID],A51,tblOperational[Merchandising_Compliance]) -> 0.752936 | M51: =L51-0.9 -> -0.147064 | N51: =AVERAGEIF(tblOperational[Rep_ID],A51,tblOperational[Product_Availability]) -> 0.784564 | O51: =N51-0.95 -> -0.165436 | P51: =IF(AND(G51>=0.9,L51>=0.8),"Healthy",IF(OR(G51<0.8,L51<0.7),"Critical","At Risk")) -> At Risk

Sheet Operational_Data
A1: Rep_ID | B1: Region_ID | C1: Region_Name | D1: Month | E1: Working_Days | F1: Attendance_Days | G1: Attendance_Rate | H1: Planned_Visits | I1: Completed_Visits | J1: Visit_Completion_Rate | K1: Visit_Gap | L1: Merchandising_Compliance | M1: Merchandising_Target | N1: Merchandising_Gap | O1: Product_Availability | P1: Availability_Target | Q1: Availability_Gap | R1: Actual_Sales | S1: Target_Multiplier | T1: Target | U1: Sales_Achievement | V1: Sales_Gap | W1: Performance_Status
A2: 321500 | B2: 1 | C2: =INDEX(tblRegions[name],MATCH(B2,tblRegions[id],0)) -> Northeast | D2: 42005 | E2: 26 | F2: 23 | G2: =F2/E2 -> 0.88461538 | H2: 480 | I2: 413 | J2: =I2/H2 -> 0.86041667 | K2: =I2-H2 -> -67 | L2: 0.7299 | M2: 0.9 | N2: =L2-M2 -> -0.1701 | O2: 0.7952 | P2: 0.95 | Q2: =O2-P2 -> -0.1548 | R2: =SUMIFS(tblCleanOrders[Sales_USD],tblCleanOrders[Rep_ID],A2,tblCleanOrders[Year],YEAR(D2),tblCleanOrders[Month],MONTH(D2)) -> 1967.79 | S2: 1.05 | T2: =INDEX(tblRepAvg[Avg_Monthly_Sales],MATCH(A2,tblRepAvg[Rep_ID],0))*S2 -> 4580.3152 | U2: =IFERROR(R2/T2,0) -> 0.4296189 | V2: =R2-T2 -> -2612.5252 | W2: =IF(AND(U2>=0.9,L2>=0.8),"Healthy",IF(OR(U2<0.8,L2<0.7),"Critical","At Risk")) -> Critical
A3: 321500 | B3: 1 | C3: =INDEX(tblRegions[name],MATCH(B3,tblRegions[id],0)) -> Northeast | D3: 42036 | E3: 26 | F3: 22 | G3: =F3/E3 -> 0.84615385 | H3: 488 | I3: 395 | J3: =I3/H3 -> 0.80942623 | K3: =I3-H3 -> -93 | L3: 0.7713 | M3: 0.9 | N3: =L3-M3 -> -0.1287 | O3: 0.8649 | P3: 0.95 | Q3: =O3-P3 -> -0.0851 | R3: =SUMIFS(tblCleanOrders[Sales_USD],tblCleanOrders[Rep_ID],A3,tblCleanOrders[Year],YEAR(D3),tblCleanOrders[Month],MONTH(D3)) -> 1857.89 | S3: 1.06 | T3: =INDEX(tblRepAvg[Avg_Monthly_Sales],MATCH(A3,tblRepAvg[Rep_ID],0))*S3 -> 4623.9373 | U3: =IFERROR(R3/T3,0) -> 0.40179827 | V3: =R3-T3 -> -2766.0473 | W3: =IF(AND(U3>=0.9,L3>=0.8),"Healthy",IF(OR(U3<0.8,L3<0.7),"Critical","At Risk")) -> Critical
A4: 321500 | B4: 1 | C4: =INDEX(tblRegions[name],MATCH(B4,tblRegions[id],0)) -> Northeast | D4: 42064 | E4: 26 | F4: 22 | G4: =F4/E4 -> 0.84615385 | H4: 496 | I4: 433 | J4: =I4/H4 -> 0.87298387 | K4: =I4-H4 -> -63 | L4: 0.722 | M4: 0.9 | N4: =L4-M4 -> -0.178 | O4: 0.7934 | P4: 0.95 | Q4: =O4-P4 -> -0.1566 | R4: =SUMIFS(tblCleanOrders[Sales_USD],tblCleanOrders[Rep_ID],A4,tblCleanOrders[Year],YEAR(D4),tblCleanOrders[Month],MONTH(D4)) -> 1857.85 | S4: 1.07 | T4: =INDEX(tblRepAvg[Avg_Monthly_Sales],MATCH(A4,tblRepAvg[Rep_ID],0))*S4 -> 4667.5593 | U4: =IFERROR(R4/T4,0) -> 0.39803457 | V4: =R4-T4 -> -2809.7093 | W4: =IF(AND(U4>=0.9,L4>=0.8),"Healthy",IF(OR(U4<0.8,L4<0.7),"Critical","At Risk")) -> Critical
A5: 321500 | B5: 1 | C5: =INDEX(tblRegions[name],MATCH(B5,tblRegions[id],0)) -> Northeast | D5: 42095 | E5: 26 | F5: 23 | G5: =F5/E5 -> 0.88461538 | H5: 504 | I5: 433 | J5: =I5/H5 -> 0.85912698 | K5: =I5-H5 -> -71 | L5: 0.8058 | M5: 0.9 | N5: =L5-M5 -> -0.0942 | O5: 0.8455 | P5: 0.95 | Q5: =O5-P5 -> -0.1045 | R5: =SUMIFS(tblCleanOrders[Sales_USD],tblCleanOrders[Rep_ID],A5,tblCleanOrders[Year],YEAR(D5),tblCleanOrders[Month],MONTH(D5)) -> 1801.7 | S5: 1.08 | T5: =INDEX(tblRepAvg[Avg_Monthly_Sales],MATCH(A5,tblRepAvg[Rep_ID],0))*S5 -> 4711.1814 | U5: =IFERROR(R5/T5,0) -> 0.38243061 | V5: =R5-T5 -> -2909.4814 | W5: =IF(AND(U5>=0.9,L5>=0.8),"Healthy",IF(OR(U5<0.8,L5<0.7),"Critical","At Risk")) -> Critical
A6: 321500 | B6: 1 | C6: =INDEX(tblRegions[name],MATCH(B6,tblRegions[id],0)) -> Northeast | D6: 42125 | E6: 26 | F6: 22 | G6: =F6/E6 -> 0.84615385 | H6: 480 | I6: 392 | J6: =I6/H6 -> 0.81666667 | K6: =I6-H6 -> -88 | L6: 0.811 | M6: 0.9 | N6: =L6-M6 -> -0.089 | O6: 0.8118 | P6: 0.95 | Q6: =O6-P6 -> -0.1382 | R6: =SUMIFS(tblCleanOrders[Sales_USD],tblCleanOrders[Rep_ID],A6,tblCleanOrders[Year],YEAR(D6),tblCleanOrders[Month],MONTH(D6)) -> 2189.39 | S6: 1.09 | T6: =INDEX(tblRepAvg[Avg_Monthly_Sales],MATCH(A6,tblRepAvg[Rep_ID],0))*S6 -> 4754.8034 | U6: =IFERROR(R6/T6,0) -> 0.46045857 | V6: =R6-T6 -> -2565.4134 | W6: =IF(AND(U6>=0.9,L6>=0.8),"Healthy",IF(OR(U6<0.8,L6<0.7),"Critical","At Risk")) -> Critical
A7: 321500 | B7: 1 | C7: =INDEX(tblRegions[name],MATCH(B7,tblRegions[id],0)) -> Northeast | D7: 42156 | E7: 26 | F7: 22 | G7: =F7/E7 -> 0.84615385 | H7: 488 | I7: 385 | J7: =I7/H7 -> 0.78893443 | K7: =I7-H7 -> -103 | L7: 0.7488 | M7: 0.9 | N7: =L7-M7 -> -0.1512 | O7: 0.8266 | P7: 0.95 | Q7: =O7-P7 -> -0.1234 | R7: =SUMIFS(tblCleanOrders[Sales_USD],tblCleanOrders[Rep_ID],A7,tblCleanOrders[Year],YEAR(D7),tblCleanOrders[Month],MONTH(D7)) -> 1764.28 | S7: 1.1 | T7: =INDEX(tblRepAvg[Avg_Monthly_Sales],MATCH(A7,tblRepAvg[Rep_ID],0))*S7 -> 4798.4255 | U7: =IFERROR(R7/T7,0) -> 0.36767894 | V7: =R7-T7 -> -3034.1455 | W7: =IF(AND(U7>=0.9,L7>=0.8),"Healthy",IF(OR(U7<0.8,L7<0.7),"Critical","At Risk")) -> Critical
A8: 321500 | B8: 1 | C8: =INDEX(tblRegions[name],MATCH(B8,tblRegions[id],0)) -> Northeast | D8: 42186 | E8: 26 | F8: 23 | G8: =F8/E8 -> 0.88461538 | H8: 496 | I8: 428 | J8: =I8/H8 -> 0.86290323 | K8: =I8-H8 -> -68 | L8: 0.766 | M8: 0.9 | N8: =L8-M8 -> -0.134 | O8: 0.8173 | P8: 0.95 | Q8: =O8-P8 -> -0.1327 | R8: =SUMIFS(tblCleanOrders[Sales_USD],tblCleanOrders[Rep_ID],A8,tblCleanOrders[Year],YEAR(D8),tblCleanOrders[Month],MONTH(D8)) -> 1884.17 | S8: 1.11 | T8: =INDEX(tblRepAvg[Avg_Monthly_Sales],MATCH(A8,tblRepAvg[Rep_ID],0))*S8 -> 4842.0475 | U8: =IFERROR(R8/T8,0) -> 0.3891267 | V8: =R8-T8 -> -2957.8775 | W8: =IF(AND(U8>=0.9,L8>=0.8),"Healthy",IF(OR(U8<0.8,L8<0.7),"Critical","At Risk")) -> Critical
A9: 321500 | B9: 1 | C9: =INDEX(tblRegions[name],MATCH(B9,tblRegions[id],0)) -> Northeast | D9: 42217 | E9: 26 | F9: 23 | G9: =F9/E9 -> 0.88461538 | H9: 504 | I9: 415 | J9: =I9/H9 -> 0.8234127 | K9: =I9-H9 -> -89 | L9: 0.7969 | M9: 0.9 | N9: =L9-M9 -> -0.1031 | O9: 0.7932 | P9: 0.95 | Q9: =O9-P9 -> -0.1568 | R9: =SUMIFS(tblCleanOrders[Sales_USD],tblCleanOrders[Rep_ID],A9,tblCleanOrders[Year],YEAR(D9),tblCleanOrders[Month],MONTH(D9)) -> 1967.71 | S9: 1.12 | T9: =INDEX(tblRepAvg[Avg_Monthly_Sales],MATCH(A9,tblRepAvg[Rep_ID],0))*S9 -> 4885.6696 | U9: =IFERROR(R9/T9,0) -> 0.40275134 | V9: =R9-T9 -> -2917.9596 | W9: =IF(AND(U9>=0.9,L9>=0.8),"Healthy",IF(OR(U9<0.8,L9<0.7),"Critical","At Risk")) -> Critical
A10: 321500 | B10: 1 | C10: =INDEX(tblRegions[name],MATCH(B10,tblRegions[id],0)) -> Northeast | D10: 42248 | E10: 26 | F10: 22 | G10: =F10/E10 -> 0.84615385 | H10: 480 | I10: 393 | J10: =I10/H10 -> 0.81875 | K10: =I10-H10 -> -87 | L10: 0.7391 | M10: 0.9 | N10: =L10-M10 -> -0.1609 | O10: 0.8248 | P10: 0.95 | Q10: =O10-P10 -> -0.1252 | R10: =SUMIFS(tblCleanOrders[Sales_USD],tblCleanOrders[Rep_ID],A10,tblCleanOrders[Year],YEAR(D10),tblCleanOrders[Month],MONTH(D10)) -> 1404.66 | S10: 1.13 | T10: =INDEX(tblRepAvg[Avg_Monthly_Sales],MATCH(A10,tblRepAvg[Rep_ID],0))*S10 -> 4929.2916 | U10: =IFERROR(R10/T10,0) -> 0.28496184 | V10: =R10-T10 -> -3524.6316 | W10: =IF(AND(U10>=0.9,L10>=0.8),"Healthy",IF(OR(U10<0.8,L10<0.7),"Critical","At Risk")) -> Critical
A11: 321500 | B11: 1 | C11: =INDEX(tblRegions[name],MATCH(B11,tblRegions[id],0)) -> Northeast | D11: 42278 | E11: 26 | F11: 22 | G11: =F11/E11 -> 0.84615385 | H11: 488 | I11: 408 | J11: =I11/H11 -> 0.83606557 | K11: =I11-H11 -> -80 | L11: 0.7978 | M11: 0.9 | N11: =L11-M11 -> -0.1022 | O11: 0.8321 | P11: 0.95 | Q11: =O11-P11 -> -0.1179 | R11: =SUMIFS(tblCleanOrders[Sales_USD],tblCleanOrders[Rep_ID],A11,tblCleanOrders[Year],YEAR(D11),tblCleanOrders[Month],MONTH(D11)) -> 2440.49 | S11: 1.14 | T11: =INDEX(tblRepAvg[Avg_Monthly_Sales],MATCH(A11,tblRepAvg[Rep_ID],0))*S11 -> 4972.9137 | U11: =IFERROR(R11/T11,0) -> 0.49075656 | V11: =R11-T11 -> -2532.4237 | W11: =IF(AND(U11>=0.9,L11>=0.8),"Healthy",IF(OR(U11<0.8,L11<0.7),"Critical","At Risk")) -> Critical
A12: 321500 | B12: 1 | C12: =INDEX(tblRegions[name],MATCH(B12,tblRegions[id],0)) -> Northeast | D12: 42309 | E12: 26 | F12: 23 | G12: =F12/E12 -> 0.88461538 | H12: 496 | I12: 412 | J12: =I12/H12 -> 0.83064516 | K12: =I12-H12 -> -84 | L12: 0.7661 | M12: 0.9 | N12: =L12-M12 -> -0.1339 | O12: 0.809 | P12: 0.95 | Q12: =O12-P12 -> -0.141 | R12: =SUMIFS(tblCleanOrders[Sales_USD],tblCleanOrders[Rep_ID],A12,tblCleanOrders[Year],YEAR(D12),tblCleanOrders[Month],MONTH(D12)) -> 2197.39 | S12: 1.15 | T12: =INDEX(tblRepAvg[Avg_Monthly_Sales],MATCH(A12,tblRepAvg[Rep_ID],0))*S12 -> 5016.5357 | U12: =IFERROR(R12/T12,0) -> 0.43802937 | V12: =R12-T12 -> -2819.1457 | W12: =IF(AND(U12>=0.9,L12>=0.8),"Healthy",IF(OR(U12<0.8,L12<0.7),"Critical","At Risk")) -> Critical
A13: 321500 | B13: 1 | C13: =INDEX(tblRegions[name],MATCH(B13,tblRegions[id],0)) -> Northeast | D13: 42339 | E13: 26 | F13: 21 | G13: =F13/E13 -> 0.80769231 | H13: 504 | I13: 392 | J13: =I13/H13 -> 0.77777778 | K13: =I13-H13 -> -112 | L13: 0.7346 | M13: 0.9 | N13: =L13-M13 -> -0.1654 | O13: 0.7721 | P13: 0.95 | Q13: =O13-P13 -> -0.1779 | R13: =SUMIFS(tblCleanOrders[Sales_USD],tblCleanOrders[Rep_ID],A13,tblCleanOrders[Year],YEAR(D13),tblCleanOrders[Month],MONTH(D13)) -> 2481.71 | S13: 1.05 | T13: =INDEX(tblRepAvg[Avg_Monthly_Sales],MATCH(A13,tblRepAvg[Rep_ID],0))*S13 -> 4580.3152 | U13: =IFERROR(R13/T13,0) -> 0.54182078 | V13: =R13-T13 -> -2098.6052 | W13: =IF(AND(U13>=0.9,L13>=0.8),"Healthy",IF(OR(U13<0.8,L13<0.7),"Critical","At Risk")) -> Critical
... A1251: 321990 | B1251: 4 | C1251: =INDEX(tblRegions[name],MATCH(B1251,tblRegions[id],0)) -> West | D1251: 42736 | E1251: 26 | F1251: 23 | G1251: =F1251/E1251 -> 0.88461538 | H1251: 480 | I1251: 360 | J1251: =I1251/H1251 -> 0.75 | K1251: =I1251-H1251 -> -120 | L1251: 0.7334 | M1251: 0.9 | N1251: =L1251-M1251 -> -0.1666 | O1251: 0.7999 | P1251: 0.95 | Q1251: =O1251-P1251 -> -0.1501 | R1251: =SUMIFS(tblCleanOrders[Sales_USD],tblCleanOrders[Rep_ID],A1251,tblCleanOrders[Year],YEAR(D1251),tblCleanOrders[Month],MONTH(D1251)) -> 0 | S1251: 1.11 | T1251: =INDEX(tblRepAvg[Avg_Monthly_Sales],MATCH(A1251,tblRepAvg[Rep_ID],0))*S1251 -> 19832.752 | U1251: =IFERROR(R1251/T1251,0) -> 0 | V1251: =R1251-T1251 -> -19832.752 | W1251: =IF(AND(U1251>=0.9,L1251>=0.8),"Healthy",IF(OR(U1251<0.8,L1251<0.7),"Critical","At Risk")) -> Critical

Sheet Rep_Performance
A1: Rep_ID | B1: Rep_Name | C1: Region | D1: Total_Sales | E1: Total_Orders
A2: =Raw_Reps!A32 -> 321800 | B2: =Raw_Reps!B32 -> Earlie Schleusner | C2: =INDEX(tblRegions[name],MATCH(Raw_Reps!C32,tblRegions[id],0)) -> Southeast | D2: =SUMIF(tblCleanOrders[Rep_ID],A2,tblCleanOrders[Sales_USD]) -> 506470.92 | E2: =COUNTIF(tblCleanOrders[Rep_ID],A2) -> 202
A3: =Raw_Reps!A33 -> 321810 | B3: =Raw_Reps!B33 -> Moon Torian | C3: =INDEX(tblRegions[name],MATCH(Raw_Reps!C33,tblRegions[id],0)) -> Southeast | D3: =SUMIF(tblCleanOrders[Rep_ID],A3,tblCleanOrders[Sales_USD]) -> 474372.08 | E3: =COUNTIF(tblCleanOrders[Rep_ID],A3) -> 167
A4: =Raw_Reps!A36 -> 321840 | B4: =Raw_Reps!B36 -> Vernita Plump | C4: =INDEX(tblRegions[name],MATCH(Raw_Reps!C36,tblRegions[id],0)) -> Southeast | D4: =SUMIF(tblCleanOrders[Rep_ID],A4,tblCleanOrders[Sales_USD]) -> 472044.16 | E4: =COUNTIF(tblCleanOrders[Rep_ID],A4) -> 184
A5: =Raw_Reps!A16 -> 321640 | B5: =Raw_Reps!B16 -> Tia Amato | C5: =INDEX(tblRegions[name],MATCH(Raw_Reps!C16,tblRegions[id],0)) -> Northeast | D5: =SUMIF(tblCleanOrders[Rep_ID],A5,tblCleanOrders[Sales_USD]) -> 466213.64 | E5: =COUNTIF(tblCleanOrders[Rep_ID],A5) -> 155
A6: =Raw_Reps!A51 -> 321990 | B6: =Raw_Reps!B51 -> Dawna Agnew | C6: =INDEX(tblRegions[name],MATCH(Raw_Reps!C51,tblRegions[id],0)) -> West | D6: =SUMIF(tblCleanOrders[Rep_ID],A6,tblCleanOrders[Sales_USD]) -> 410948.92 | E6: =COUNTIF(tblCleanOrders[Rep_ID],A6) -> 73
A7: =Raw_Reps!A48 -> 321960 | B7: =Raw_Reps!B48 -> Maryanna Fiorentino | C7: =INDEX(tblRegions[name],MATCH(Raw_Reps!C48,tblRegions[id],0)) -> West | D7: =SUMIF(tblCleanOrders[Rep_ID],A7,tblCleanOrders[Sales_USD]) -> 363890.51 | E7: =COUNTIF(tblCleanOrders[Rep_ID],A7) -> 90
A8: =Raw_Reps!A41 -> 321890 | B8: =Raw_Reps!B41 -> Nelle Meaux | C8: =INDEX(tblRegions[name],MATCH(Raw_Reps!C41,tblRegions[id],0)) -> Southeast | D8: =SUMIF(tblCleanOrders[Rep_ID],A8,tblCleanOrders[Sales_USD]) -> 359779.88 | E8: =COUNTIF(tblCleanOrders[Rep_ID],A8) -> 151
A9: =Raw_Reps!A47 -> 321950 | B9: =Raw_Reps!B47 -> Elwood Shutt | C9: =INDEX(tblRegions[name],MATCH(Raw_Reps!C47,tblRegions[id],0)) -> West | D9: =SUMIF(tblCleanOrders[Rep_ID],A9,tblCleanOrders[Sales_USD]) -> 346698.05 | E9: =COUNTIF(tblCleanOrders[Rep_ID],A9) -> 108
A10: =Raw_Reps!A28 -> 321760 | B10: =Raw_Reps!B28 -> Delilah Krum | C10: =INDEX(tblRegions[name],MATCH(Raw_Reps!C28,tblRegions[id],0)) -> Midwest | D10: =SUMIF(tblCleanOrders[Rep_ID],A10,tblCleanOrders[Sales_USD]) -> 315747.89 | E10: =COUNTIF(tblCleanOrders[Rep_ID],A10) -> 126
A11: =Raw_Reps!A26 -> 321740 | B11: =Raw_Reps!B26 -> Charles Bidwell | C11: =INDEX(tblRegions[name],MATCH(Raw_Reps!C26,tblRegions[id],0)) -> Midwest | D11: =SUMIF(tblCleanOrders[Rep_ID],A11,tblCleanOrders[Sales_USD]) -> 306753.04 | E11: =COUNTIF(tblCleanOrders[Rep_ID],A11) -> 129
A12: =Raw_Reps!A27 -> 321750 | B12: =Raw_Reps!B27 -> Cliff Meints | C12: =INDEX(tblRegions[name],MATCH(Raw_Reps!C27,tblRegions[id],0)) -> Midwest | D12: =SUMIF(tblCleanOrders[Rep_ID],A12,tblCleanOrders[Sales_USD]) -> 301222.13 | E12: =COUNTIF(tblCleanOrders[Rep_ID],A12) -> 92
A13: =Raw_Reps!A35 -> 321830 | B13: =Raw_Reps!B35 -> Maren Musto | C13: =INDEX(tblRegions[name],MATCH(Raw_Reps!C35,tblRegions[id],0)) -> Southeast | D13: =SUMIF(tblCleanOrders[Rep_ID],A13,tblCleanOrders[Sales_USD]) -> 297420.99 | E13: =COUNTIF(tblCleanOrders[Rep_ID],A13) -> 139
A14: =Raw_Reps!A50 -> 321980 | B14: =Raw_Reps!B50 -> Micha Woodford | C14: =INDEX(tblRegions[name],MATCH(Raw_Reps!C50,tblRegions[id],0)) -> West | D14: =SUMIF(tblCleanOrders[Rep_ID],A14,tblCleanOrders[Sales_USD]) -> 296821.11 | E14: =COUNTIF(tblCleanOrders[Rep_ID],A14) -> 101
A15: =Raw_Reps!A34 -> 321820 | B15: =Raw_Reps!B34 -> Dorotha Seawell | C15: =INDEX(tblRegions[name],MATCH(Raw_Reps!C34,tblRegions[id],0)) -> Southeast | D15: =SUMIF(tblCleanOrders[Rep_ID],A15,tblCleanOrders[Sales_USD]) -> 287489.56 | E15: =COUNTIF(tblCleanOrders[Rep_ID],A15) -> 134
A16: =Raw_Reps!A10 -> 321580 | B16: =Raw_Reps!B10 -> Sibyl Lauria | C16: =INDEX(tblRegions[name],MATCH(Raw_Reps!C10,tblRegions[id],0)) -> Northeast | D16: =SUMIF(tblCleanOrders[Rep_ID],A16,tblCleanOrders[Sales_USD]) -> 269561.74 | E16: =COUNTIF(tblCleanOrders[Rep_ID],A16) -> 116
A17: =Raw_Reps!A21 -> 321690 | B17: =Raw_Reps!B21 -> Gianna Dossey | C17: =INDEX(tblRegions[name],MATCH(Raw_Reps!C21,tblRegions[id],0)) -> Northeast | D17: =SUMIF(tblCleanOrders[Rep_ID],A17,tblCleanOrders[Sales_USD]) -> 266223.71 | E17: =COUNTIF(tblCleanOrders[Rep_ID],A17) -> 111
A18: =Raw_Reps!A43 -> 321910 | B18: =Raw_Reps!B43 -> Brandie Riva | C18: =INDEX(tblRegions[name],MATCH(Raw_Reps!C43,tblRegions[id],0)) -> West | D18: =SUMIF(tblCleanOrders[Rep_ID],A18,tblCleanOrders[Sales_USD]) -> 263542.85 | E18: =COUNTIF(tblCleanOrders[Rep_ID],A18) -> 96
A19: =Raw_Reps!A20 -> 321680 | B19: =Raw_Reps!B20 -> Elna Condello | C19: =INDEX(tblRegions[name],MATCH(Raw_Reps!C20,tblRegions[id],0)) -> Northeast | D19: =SUMIF(tblCleanOrders[Rep_ID],A19,tblCleanOrders[Sales_USD]) -> 259329.99 | E19: =COUNTIF(tblCleanOrders[Rep_ID],A19) -> 111
A20: =Raw_Reps!A46 -> 321940 | B20: =Raw_Reps!B46 -> Arica Stoltzfus | C20: =INDEX(tblRegions[name],MATCH(Raw_Reps!C46,tblRegions[id],0)) -> West | D20: =SUMIF(tblCleanOrders[Rep_ID],A20,tblCleanOrders[Sales_USD]) -> 246370.99 | E20: =COUNTIF(tblCleanOrders[Rep_ID],A20) -> 72
A21: =Raw_Reps!A4 -> 321520 | B21: =Raw_Reps!B4 -> Michel Averette | C21: =INDEX(tblRegions[name],MATCH(Raw_Reps!C4,tblRegions[id],0)) -> Northeast | D21: =SUMIF(tblCleanOrders[Rep_ID],A21,tblCleanOrders[Sales_USD]) -> 238183.17 | E21: =COUNTIF(tblCleanOrders[Rep_ID],A21) -> 111
A22: =Raw_Reps!A11 -> 321590 | B22: =Raw_Reps!B11 -> Necole Victory | C22: =INDEX(tblRegions[name],MATCH(Raw_Reps!C11,tblRegions[id],0)) -> Northeast | D22: =SUMIF(tblCleanOrders[Rep_ID],A22,tblCleanOrders[Sales_USD]) -> 236570.16 | E22: =COUNTIF(tblCleanOrders[Rep_ID],A22) -> 89
A23: =Raw_Reps!A37 -> 321850 | B23: =Raw_Reps!B37 -> Calvin Ollison | C23: =INDEX(tblRegions[name],MATCH(Raw_Reps!C37,tblRegions[id],0)) -> Southeast | D23: =SUMIF(tblCleanOrders[Rep_ID],A23,tblCleanOrders[Sales_USD]) -> 227979.48 | E23: =COUNTIF(tblCleanOrders[Rep_ID],A23) -> 121
A24: =Raw_Reps!A22 -> 321700 | B24: =Raw_Reps!B22 -> Debroah Wardle | C24: =INDEX(tblRegions[name],MATCH(Raw_Reps!C22,tblRegions[id],0)) -> Northeast | D24: =SUMIF(tblCleanOrders[Rep_ID],A24,tblCleanOrders[Sales_USD]) -> 221615.65 | E24: =COUNTIF(tblCleanOrders[Rep_ID],A24) -> 69
A25: =Raw_Reps!A12 -> 321600 | B25: =Raw_Reps!B12 -> Ernestine Pickron | C25: =INDEX(tblRegions[name],MATCH(Raw_Reps!C12,tblRegions[id],0)) -> Northeast | D25: =SUMIF(tblCleanOrders[Rep_ID],A25,tblCleanOrders[Sales_USD]) -> 214979.49 | E25: =COUNTIF(tblCleanOrders[Rep_ID],A25) -> 56
A26: =Raw_Reps!A15 -> 321630 | B26: =Raw_Reps!B15 -> Julia Behrman | C26: =INDEX(tblRegions[name],MATCH(Raw_Reps!C15,tblRegions[id],0)) -> Northeast | D26: =SUMIF(tblCleanOrders[Rep_ID],A26,tblCleanOrders[Sales_USD]) -> 209403.2 | E26: =COUNTIF(tblCleanOrders[Rep_ID],A26) -> 76
A27: =Raw_Reps!A9 -> 321570 | B27: =Raw_Reps!B9 -> Shawanda Selke | C27: =INDEX(tblRegions[name],MATCH(Raw_Reps!C9,tblRegions[id],0)) -> Northeast | D27: =SUMIF(tblCleanOrders[Rep_ID],A27,tblCleanOrders[Sales_USD]) -> 199381.82 | E27: =COUNTIF(tblCleanOrders[Rep_ID],A27) -> 63
A28: =Raw_Reps!A42 -> 321900 | B28: =Raw_Reps!B42 -> Soraya Fulton | C28: =INDEX(tblRegions[name],MATCH(Raw_Reps!C42,tblRegions[id],0)) -> West | D28: =SUMIF(tblCleanOrders[Rep_ID],A28,tblCleanOrders[Sales_USD]) -> 164177.13 | E28: =COUNTIF(tblCleanOrders[Rep_ID],A28) -> 35
A29: =Raw_Reps!A38 -> 321860 | B29: =Raw_Reps!B38 -> Saran Ram | C29: =INDEX(tblRegions[name],MATCH(Raw_Reps!C38,tblRegions[id],0)) -> Southeast | D29: =SUMIF(tblCleanOrders[Rep_ID],A29,tblCleanOrders[Sales_USD]) -> 163499.04 | E29: =COUNTIF(tblCleanOrders[Rep_ID],A29) -> 67
A30: =Raw_Reps!A49 -> 321970 | B30: =Raw_Reps!B49 -> Georgianna Chisholm | C30: =INDEX(tblRegions[name],MATCH(Raw_Reps!C49,tblRegions[id],0)) -> West | D30: =SUMIF(tblCleanOrders[Rep_ID],A30,tblCleanOrders[Sales_USD]) -> 160911.82 | E30: =COUNTIF(tblCleanOrders[Rep_ID],A30) -> 80
A31: =Raw_Reps!A2 -> 321500 | B31: =Raw_Reps!B2 -> Samuel Racine | C31: =INDEX(tblRegions[name],MATCH(Raw_Reps!C2,tblRegions[id],0)) -> Northeast | D31: =SUMIF(tblCleanOrders[Rep_ID],A31,tblCleanOrders[Sales_USD]) -> 157039.38 | E31: =COUNTIF(tblCleanOrders[Rep_ID],A31) -> 83
A32: =Raw_Reps!A13 -> 321610 | B32: =Raw_Reps!B13 -> Ayesha Monica | C32: =INDEX(tblRegions[name],MATCH(Raw_Reps!C13,tblRegions[id],0)) -> Northeast | D32: =SUMIF(tblCleanOrders[Rep_ID],A32,tblCleanOrders[Sales_USD]) -> 146915.26 | E32: =COUNTIF(tblCleanOrders[Rep_ID],A32) -> 54
A33: =Raw_Reps!A45 -> 321930 | B33: =Raw_Reps!B45 -> Hilma Busick | C33: =INDEX(tblRegions[name],MATCH(Raw_Reps!C45,tblRegions[id],0)) -> West | D33: =SUMIF(tblCleanOrders[Rep_ID],A33,tblCleanOrders[Sales_USD]) -> 130558.53 | E33: =COUNTIF(tblCleanOrders[Rep_ID],A33) -> 70
A34: =Raw_Reps!A39 -> 321870 | B34: =Raw_Reps!B39 -> Derrick Boggess | C34: =INDEX(tblRegions[name],MATCH(Raw_Reps!C39,tblRegions[id],0)) -> Southeast | D34: =SUMIF(tblCleanOrders[Rep_ID],A34,tblCleanOrders[Sales_USD]) -> 127986.57 | E34: =COUNTIF(tblCleanOrders[Rep_ID],A34) -> 62
A35: =Raw_Reps!A3 -> 321510 | B35: =Raw_Reps!B3 -> Eugena Esser | C35: =INDEX(tblRegions[name],MATCH(Raw_Reps!C3,tblRegions[id],0)) -> Northeast | D35: =SUMIF(tblCleanOrders[Rep_ID],A35,tblCleanOrders[Sales_USD]) -> 127815.82 | E35: =COUNTIF(tblCleanOrders[Rep_ID],A35) -> 69
A36: =Raw_Reps!A17 -> 321650 | B36: =Raw_Reps!B17 -> Akilah Drinkard | C36: =INDEX(tblRegions[name],MATCH(Raw_Reps!C17,tblRegions[id],0)) -> Northeast | D36: =SUMIF(tblCleanOrders[Rep_ID],A36,tblCleanOrders[Sales_USD]) -> 120016.11 | E36: =COUNTIF(tblCleanOrders[Rep_ID],A36) -> 43
A37: =Raw_Reps!A31 -> 321790 | B37: =Raw_Reps!B31 -> Cordell Rieder | C37: =INDEX(tblRegions[name],MATCH(Raw_Reps!C31,tblRegions[id],0)) -> Midwest | D37: =SUMIF(tblCleanOrders[Rep_ID],A37,tblCleanOrders[Sales_USD]) -> 105545.8 | E37: =COUNTIF(tblCleanOrders[Rep_ID],A37) -> 57
A38: =Raw_Reps!A23 -> 321710 | B38: =Raw_Reps!B23 -> Sherlene Wetherington | C38: =INDEX(tblRegions[name],MATCH(Raw_Reps!C23,tblRegions[id],0)) -> Midwest | D38: =SUMIF(tblCleanOrders[Rep_ID],A38,tblCleanOrders[Sales_USD]) -> 104177.49 | E38: =COUNTIF(tblCleanOrders[Rep_ID],A38) -> 40
A39: =Raw_Reps!A5 -> 321530 | B39: =Raw_Reps!B5 -> Renetta Carew | C39: =INDEX(tblRegions[name],MATCH(Raw_Reps!C5,tblRegions[id],0)) -> Northeast | D39: =SUMIF(tblCleanOrders[Rep_ID],A39,tblCleanOrders[Sales_USD]) -> 97134.47 | E39: =COUNTIF(tblCleanOrders[Rep_ID],A39) -> 52
A40: =Raw_Reps!A7 -> 321550 | B40: =Raw_Reps!B7 -> Lavera Oles | C40: =INDEX(tblRegions[name],MATCH(Raw_Reps!C7,tblRegions[id],0)) -> Northeast | D40: =SUMIF(tblCleanOrders[Rep_ID],A40,tblCleanOrders[Sales_USD]) -> 94845.03 | E40: =COUNTIF(tblCleanOrders[Rep_ID],A40) -> 42
A41: =Raw_Reps!A18 -> 321660 | B41: =Raw_Reps!B18 -> Silvana Virden | C41: =INDEX(tblRegions[name],MATCH(Raw_Reps!C18,tblRegions[id],0)) -> Northeast | D41: =SUMIF(tblCleanOrders[Rep_ID],A41,tblCleanOrders[Sales_USD]) -> 94772.32 | E41: =COUNTIF(tblCleanOrders[Rep_ID],A41) -> 38
A42: =Raw_Reps!A44 -> 321920 | B42: =Raw_Reps!B44 -> Marquetta Laycock | C42: =INDEX(tblRegions[name],MATCH(Raw_Reps!C44,tblRegions[id],0)) -> West | D42: =SUMIF(tblCleanOrders[Rep_ID],A42,tblCleanOrders[Sales_USD]) -> 91534.77 | E42: =COUNTIF(tblCleanOrders[Rep_ID],A42) -> 36
A43: =Raw_Reps!A25 -> 321730 | B43: =Raw_Reps!B25 -> Carletta Kosinski | C43: =INDEX(tblRegions[name],MATCH(Raw_Reps!C25,tblRegions[id],0)) -> Midwest | D43: =SUMIF(tblCleanOrders[Rep_ID],A43,tblCleanOrders[Sales_USD]) -> 78105.02 | E43: =COUNTIF(tblCleanOrders[Rep_ID],A43) -> 36
A44: =Raw_Reps!A40 -> 321880 | B44: =Raw_Reps!B40 -> Babette Soukup | C44: =INDEX(tblRegions[name],MATCH(Raw_Reps!C40,tblRegions[id],0)) -> Southeast | D44: =SUMIF(tblCleanOrders[Rep_ID],A44,tblCleanOrders[Sales_USD]) -> 73042.7 | E44: =COUNTIF(tblCleanOrders[Rep_ID],A44) -> 38
A45: =Raw_Reps!A24 -> 321720 | B45: =Raw_Reps!B24 -> Chau Rowles | C45: =INDEX(tblRegions[name],MATCH(Raw_Reps!C24,tblRegions[id],0)) -> Midwest | D45: =SUMIF(tblCleanOrders[Rep_ID],A45,tblCleanOrders[Sales_USD]) -> 72321.9 | E45: =COUNTIF(tblCleanOrders[Rep_ID],A45) -> 43
A46: =Raw_Reps!A6 -> 321540 | B46: =Raw_Reps!B6 -> Cara Clarke | C46: =INDEX(tblRegions[name],MATCH(Raw_Reps!C6,tblRegions[id],0)) -> Northeast | D46: =SUMIF(tblCleanOrders[Rep_ID],A46,tblCleanOrders[Sales_USD]) -> 69428.72 | E46: =COUNTIF(tblCleanOrders[Rep_ID],A46) -> 35
A47: =Raw_Reps!A14 -> 321620 | B47: =Raw_Reps!B14 -> Retha Sears | C47: =INDEX(tblRegions[name],MATCH(Raw_Reps!C14,tblRegions[id],0)) -> Northeast | D47: =SUMIF(tblCleanOrders[Rep_ID],A47,tblCleanOrders[Sales_USD]) -> 53699.03 | E47: =COUNTIF(tblCleanOrders[Rep_ID],A47) -> 38
A48: =Raw_Reps!A29 -> 321770 | B48: =Raw_Reps!B29 -> Kathleen Lalonde | C48: =INDEX(tblRegions[name],MATCH(Raw_Reps!C29,tblRegions[id],0)) -> Midwest | D48: =SUMIF(tblCleanOrders[Rep_ID],A48,tblCleanOrders[Sales_USD]) -> 43904.51 | E48: =COUNTIF(tblCleanOrders[Rep_ID],A48) -> 21
A49: =Raw_Reps!A8 -> 321560 | B49: =Raw_Reps!B8 -> Elba Felder | C49: =INDEX(tblRegions[name],MATCH(Raw_Reps!C8,tblRegions[id],0)) -> Northeast | D49: =SUMIF(tblCleanOrders[Rep_ID],A49,tblCleanOrders[Sales_USD]) -> 40874.66 | E49: =COUNTIF(tblCleanOrders[Rep_ID],A49) -> 39
A50: =Raw_Reps!A30 -> 321780 | B50: =Raw_Reps!B30 -> Julie Starr | C50: =INDEX(tblRegions[name],MATCH(Raw_Reps!C30,tblRegions[id],0)) -> Midwest | D50: =SUMIF(tblCleanOrders[Rep_ID],A50,tblCleanOrders[Sales_USD]) -> 35914.15 | E50: =COUNTIF(tblCleanOrders[Rep_ID],A50) -> 22
A51: =Raw_Reps!A19 -> 321670 | B51: =Raw_Reps!B19 -> Nakesha Renn | C51: =INDEX(tblRegions[name],MATCH(Raw_Reps!C19,tblRegions[id],0)) -> Northeast | D51: =SUMIF(tblCleanOrders[Rep_ID],A51,tblCleanOrders[Sales_USD]) -> 15717.12 | E51: =COUNTIF(tblCleanOrders[Rep_ID],A51) -> 8

Sheet Clean_Orders
A1: Order_ID | B1: Account_ID | C1: Order_Date | D1: Year | E1: Month | F1: Month_Name | G1: Total_Quantity | H1: Sales_USD | I1: Rep_ID | J1: Region_ID | K1: Region_Name
A2: =Raw_Orders!A2 -> 1 | B2: =Raw_Orders!B2 -> 1001 | C2: =INT(Raw_Orders!C2) -> 42283 | D2: =YEAR(C2) -> 2015 | E2: =MONTH(C2) -> 10 | F2: =TEXT(C2,"mmm") -> Oct | G2: =Raw_Orders!G2 -> 169 | H2: =Raw_Orders!K2 -> 973.43 | I2: =INDEX(tblAccounts[sales_rep_id],MATCH(B2,tblAccounts[id],0)) -> 321500 | J2: =INDEX(tblReps[region_id],MATCH(I2,tblReps[id],0)) -> 1 | K2: =INDEX(tblRegions[name],MATCH(J2,tblRegions[id],0)) -> Northeast
A3: =Raw_Orders!A3 -> 2 | B3: =Raw_Orders!B3 -> 1001 | C3: =INT(Raw_Orders!C3) -> 42313 | D3: =YEAR(C3) -> 2015 | E3: =MONTH(C3) -> 11 | F3: =TEXT(C3,"mmm") -> Nov | G3: =Raw_Orders!G3 -> 288 | H3: =Raw_Orders!K3 -> 1718.03 | I3: =INDEX(tblAccounts[sales_rep_id],MATCH(B3,tblAccounts[id],0)) -> 321500 | J3: =INDEX(tblReps[region_id],MATCH(I3,tblReps[id],0)) -> 1 | K3: =INDEX(tblRegions[name],MATCH(J3,tblRegions[id],0)) -> Northeast
A4: =Raw_Orders!A4 -> 3 | B4: =Raw_Orders!B4 -> 1001 | C4: =INT(Raw_Orders!C4) -> 42342 | D4: =YEAR(C4) -> 2015 | E4: =MONTH(C4) -> 12 | F4: =TEXT(C4,"mmm") -> Dec | G4: =Raw_Orders!G4 -> 132 | H4: =Raw_Orders!K4 -> 776.18 | I4: =INDEX(tblAccounts[sales_rep_id],MATCH(B4,tblAccounts[id],0)) -> 321500 | J4: =INDEX(tblReps[region_id],MATCH(I4,tblReps[id],0)) -> 1 | K4: =INDEX(tblRegions[name],MATCH(J4,tblRegions[id],0)) -> Northeast
A5: =Raw_Orders!A5 -> 4 | B5: =Raw_Orders!B5 -> 1001 | C5: =INT(Raw_Orders!C5) -> 42371 | D5: =YEAR(C5) -> 2016 | E5: =MONTH(C5) -> 1 | F5: =TEXT(C5,"mmm") -> Jan | G5: =Raw_Orders!G5 -> 176 | H5: =Raw_Orders!K5 -> 958.24 | I5: =INDEX(tblAccounts[sales_rep_id],MATCH(B5,tblAccounts[id],0)) -> 321500 | J5: =INDEX(tblReps[region_id],MATCH(I5,tblReps[id],0)) -> 1 | K5: =INDEX(tblRegions[name],MATCH(J5,tblRegions[id],0)) -> Northeast
A6: =Raw_Orders!A6 -> 5 | B6: =Raw_Orders!B6 -> 1001 | C6: =INT(Raw_Orders!C6) -> 42401 | D6: =YEAR(C6) -> 2016 | E6: =MONTH(C6) -> 2 | F6: =TEXT(C6,"mmm") -> Feb | G6: =Raw_Orders!G6 -> 165 | H6: =Raw_Orders!K6 -> 983.49 | I6: =INDEX(tblAccounts[sales_rep_id],MATCH(B6,tblAccounts[id],0)) -> 321500 | J6: =INDEX(tblReps[region_id],MATCH(I6,tblReps[id],0)) -> 1 | K6: =INDEX(tblRegions[name],MATCH(J6,tblRegions[id],0)) -> Northeast
A7: =Raw_Orders!A7 -> 6 | B7: =Raw_Orders!B7 -> 1001 | C7: =INT(Raw_Orders!C7) -> 42431 | D7: =YEAR(C7) -> 2016 | E7: =MONTH(C7) -> 3 | F7: =TEXT(C7,"mmm") -> Mar | G7: =Raw_Orders!G7 -> 173 | H7: =Raw_Orders!K7 -> 1067.25 | I7: =INDEX(tblAccounts[sales_rep_id],MATCH(B7,tblAccounts[id],0)) -> 321500 | J7: =INDEX(tblReps[region_id],MATCH(I7,tblReps[id],0)) -> 1 | K7: =INDEX(tblRegions[name],MATCH(J7,tblRegions[id],0)) -> Northeast
A8: =Raw_Orders!A8 -> 7 | B8: =Raw_Orders!B8 -> 1001 | C8: =INT(Raw_Orders!C8) -> 42461 | D8: =YEAR(C8) -> 2016 | E8: =MONTH(C8) -> 4 | F8: =TEXT(C8,"mmm") -> Apr | G8: =Raw_Orders!G8 -> 226 | H8: =Raw_Orders!K8 -> 1498.2 | I8: =INDEX(tblAccounts[sales_rep_id],MATCH(B8,tblAccounts[id],0)) -> 321500 | J8: =INDEX(tblReps[region_id],MATCH(I8,tblReps[id],0)) -> 1 | K8: =INDEX(tblRegions[name],MATCH(J8,tblRegions[id],0)) -> Northeast
A9: =Raw_Orders!A9 -> 8 | B9: =Raw_Orders!B9 -> 1001 | C9: =INT(Raw_Orders!C9) -> 42491 | D9: =YEAR(C9) -> 2016 | E9: =MONTH(C9) -> 5 | F9: =TEXT(C9,"mmm") -> May | G9: =Raw_Orders!G9 -> 293 | H9: =Raw_Orders!K9 -> 2052.2 | I9: =INDEX(tblAccounts[sales_rep_id],MATCH(B9,tblAccounts[id],0)) -> 321500 | J9: =INDEX(tblReps[region_id],MATCH(I9,tblReps[id],0)) -> 1 | K9: =INDEX(tblRegions[name],MATCH(J9,tblRegions[id],0)) -> Northeast
A10: =Raw_Orders!A10 -> 9 | B10: =Raw_Orders!B10 -> 1001 | C10: =INT(Raw_Orders!C10) -> 42521 | D10: =YEAR(C10) -> 2016 | E10: =MONTH(C10) -> 5 | F10: =TEXT(C10,"mmm") -> May | G10: =Raw_Orders!G10 -> 129 | H10: =Raw_Orders!K10 -> 752.57 | I10: =INDEX(tblAccounts[sales_rep_id],MATCH(B10,tblAccounts[id],0)) -> 321500 | J10: =INDEX(tblReps[region_id],MATCH(I10,tblReps[id],0)) -> 1 | K10: =INDEX(tblRegions[name],MATCH(J10,tblRegions[id],0)) -> Northeast
A11: =Raw_Orders!A11 -> 10 | B11: =Raw_Orders!B11 -> 1001 | C11: =INT(Raw_Orders!C11) -> 42551 | D11: =YEAR(C11) -> 2016 | E11: =MONTH(C11) -> 6 | F11: =TEXT(C11,"mmm") -> Jun | G11: =Raw_Orders!G11 -> 148 | H11: =Raw_Orders!K11 -> 878.56 | I11: =INDEX(tblAccounts[sales_rep_id],MATCH(B11,tblAccounts[id],0)) -> 321500 | J11: =INDEX(tblReps[region_id],MATCH(I11,tblReps[id],0)) -> 1 | K11: =INDEX(tblRegions[name],MATCH(J11,tblRegions[id],0)) -> Northeast
A12: =Raw_Orders!A12 -> 11 | B12: =Raw_Orders!B12 -> 1001 | C12: =INT(Raw_Orders!C12) -> 42581 | D12: =YEAR(C12) -> 2016 | E12: =MONTH(C12) -> 7 | F12: =TEXT(C12,"mmm") -> Jul | G12: =Raw_Orders!G12 -> 137 | H12: =Raw_Orders!K12 -> 773.63 | I12: =INDEX(tblAccounts[sales_rep_id],MATCH(B12,tblAccounts[id],0)) -> 321500 | J12: =INDEX(tblReps[region_id],MATCH(I12,tblReps[id],0)) -> 1 | K12: =INDEX(tblRegions[name],MATCH(J12,tblRegions[id],0)) -> Northeast
A13: =Raw_Orders!A13 -> 12 | B13: =Raw_Orders!B13 -> 1001 | C13: =INT(Raw_Orders!C13) -> 42610 | D13: =YEAR(C13) -> 2016 | E13: =MONTH(C13) -> 8 | F13: =TEXT(C13,"mmm") -> Aug | G13: =Raw_Orders!G13 -> 196 | H13: =Raw_Orders!K13 -> 1182.61 | I13: =INDEX(tblAccounts[sales_rep_id],MATCH(B13,tblAccounts[id],0)) -> 321500 | J13: =INDEX(tblReps[region_id],MATCH(I13,tblReps[id],0)) -> 1 | K13: =INDEX(tblRegions[name],MATCH(J13,tblRegions[id],0)) -> Northeast
... A4051: =Raw_Orders!A4051 -> 4050 | B4051: =Raw_Orders!B4051 -> 4281 | C4051: =INT(Raw_Orders!C4051) -> 42402 | D4051: =YEAR(C4051) -> 2016 | E4051: =MONTH(C4051) -> 2 | F4051: =TEXT(C4051,"mmm") -> Feb | G4051: =Raw_Orders!G4051 -> 476 | H4051: =Raw_Orders!K4051 -> 2817.21 | I4051: =INDEX(tblAccounts[sales_rep_id],MATCH(B4051,tblAccounts[id],0)) -> 321930 | J4051: =INDEX(tblReps[region_id],MATCH(I4051,tblReps[id],0)) -> 4 | K4051: =INDEX(tblRegions[name],MATCH(J4051,tblRegions[id],0)) -> West

Sheet Monthly_Rep_Sales
A1: Rep_ID | B1: Year | C1: Month | D1: Monthly_Sales
A2: 321500 | B2: 2014 | C2: 1 | D2: =SUMIFS(tblCleanOrders[Sales_USD],tblCleanOrders[Rep_ID],A2,tblCleanOrders[Year],B2,tblCleanOrders[Month],C2) -> 1851.78
A3: 321500 | B3: 2014 | C3: 2 | D3: =SUMIFS(tblCleanOrders[Sales_USD],tblCleanOrders[Rep_ID],A3,tblCleanOrders[Year],B3,tblCleanOrders[Month],C3) -> 3273.34
A4: 321500 | B4: 2014 | C4: 3 | D4: =SUMIFS(tblCleanOrders[Sales_USD],tblCleanOrders[Rep_ID],A4,tblCleanOrders[Year],B4,tblCleanOrders[Month],C4) -> 1651.87
A5: 321500 | B5: 2014 | C5: 4 | D5: =SUMIFS(tblCleanOrders[Sales_USD],tblCleanOrders[Rep_ID],A5,tblCleanOrders[Year],B5,tblCleanOrders[Month],C5) -> 1809.22
A6: 321500 | B6: 2014 | C6: 5 | D6: =SUMIFS(tblCleanOrders[Sales_USD],tblCleanOrders[Rep_ID],A6,tblCleanOrders[Year],B6,tblCleanOrders[Month],C6) -> 1990.79
A7: 321500 | B7: 2014 | C7: 6 | D7: =SUMIFS(tblCleanOrders[Sales_USD],tblCleanOrders[Rep_ID],A7,tblCleanOrders[Year],B7,tblCleanOrders[Month],C7) -> 2023.49
A8: 321500 | B8: 2014 | C8: 7 | D8: =SUMIFS(tblCleanOrders[Sales_USD],tblCleanOrders[Rep_ID],A8,tblCleanOrders[Year],B8,tblCleanOrders[Month],C8) -> 1643.43
A9: 321500 | B9: 2014 | C9: 8 | D9: =SUMIFS(tblCleanOrders[Sales_USD],tblCleanOrders[Rep_ID],A9,tblCleanOrders[Year],B9,tblCleanOrders[Month],C9) -> 1926.32
A10: 321500 | B10: 2014 | C10: 9 | D10: =SUMIFS(tblCleanOrders[Sales_USD],tblCleanOrders[Rep_ID],A10,tblCleanOrders[Year],B10,tblCleanOrders[Month],C10) -> 1382.23
A11: 321500 | B11: 2014 | C11: 10 | D11: =SUMIFS(tblCleanOrders[Sales_USD],tblCleanOrders[Rep_ID],A11,tblCleanOrders[Year],B11,tblCleanOrders[Month],C11) -> 1925.51
A12: 321500 | B12: 2014 | C12: 11 | D12: =SUMIFS(tblCleanOrders[Sales_USD],tblCleanOrders[Rep_ID],A12,tblCleanOrders[Year],B12,tblCleanOrders[Month],C12) -> 1623.91
A13: 321500 | B13: 2014 | C13: 12 | D13: =SUMIFS(tblCleanOrders[Sales_USD],tblCleanOrders[Rep_ID],A13,tblCleanOrders[Year],B13,tblCleanOrders[Month],C13) -> 2070.16
... A1510: 321990 | B1510: 2016 | C1510: 12 | D1510: =SUMIFS(tblCleanOrders[Sales_USD],tblCleanOrders[Rep_ID],A1510,tblCleanOrders[Year],B1510,tblCleanOrders[Month],C1510) -> 256413.44

Sheet Rep_Avg_Sales
A1: Rep_ID | B1: Rep_Name | C1: Avg_Monthly_Sales
A2: =Raw_Reps!A2 -> 321500 | B2: =Raw_Reps!B2 -> Samuel Racine | C2: =AVERAGEIF(tblMonthlySales[Rep_ID],A2,tblMonthlySales[Monthly_Sales]) -> 4362.205
A3: =Raw_Reps!A3 -> 321510 | B3: =Raw_Reps!B3 -> Eugena Esser | C3: =AVERAGEIF(tblMonthlySales[Rep_ID],A3,tblMonthlySales[Monthly_Sales]) -> 3550.4394
A4: =Raw_Reps!A4 -> 321520 | B4: =Raw_Reps!B4 -> Michel Averette | C4: =AVERAGEIF(tblMonthlySales[Rep_ID],A4,tblMonthlySales[Monthly_Sales]) -> 6437.383
A5: =Raw_Reps!A5 -> 321530 | B5: =Raw_Reps!B5 -> Renetta Carew | C5: =AVERAGEIF(tblMonthlySales[Rep_ID],A5,tblMonthlySales[Monthly_Sales]) -> 3035.4522
A6: =Raw_Reps!A6 -> 321540 | B6: =Raw_Reps!B6 -> Cara Clarke | C6: =AVERAGEIF(tblMonthlySales[Rep_ID],A6,tblMonthlySales[Monthly_Sales]) -> 2571.4341
A7: =Raw_Reps!A7 -> 321550 | B7: =Raw_Reps!B7 -> Lavera Oles | C7: =AVERAGEIF(tblMonthlySales[Rep_ID],A7,tblMonthlySales[Monthly_Sales]) -> 3512.7789
A8: =Raw_Reps!A8 -> 321560 | B8: =Raw_Reps!B8 -> Elba Felder | C8: =AVERAGEIF(tblMonthlySales[Rep_ID],A8,tblMonthlySales[Monthly_Sales]) -> 1238.6261
A9: =Raw_Reps!A9 -> 321570 | B9: =Raw_Reps!B9 -> Shawanda Selke | C9: =AVERAGEIF(tblMonthlySales[Rep_ID],A9,tblMonthlySales[Monthly_Sales]) -> 5388.6978
A10: =Raw_Reps!A10 -> 321580 | B10: =Raw_Reps!B10 -> Sibyl Lauria | C10: =AVERAGEIF(tblMonthlySales[Rep_ID],A10,tblMonthlySales[Monthly_Sales]) -> 7285.4524
A11: =Raw_Reps!A11 -> 321590 | B11: =Raw_Reps!B11 -> Necole Victory | C11: =AVERAGEIF(tblMonthlySales[Rep_ID],A11,tblMonthlySales[Monthly_Sales]) -> 6393.7881
A12: =Raw_Reps!A12 -> 321600 | B12: =Raw_Reps!B12 -> Ernestine Pickron | C12: =AVERAGEIF(tblMonthlySales[Rep_ID],A12,tblMonthlySales[Monthly_Sales]) -> 5810.2565
A13: =Raw_Reps!A13 -> 321610 | B13: =Raw_Reps!B13 -> Ayesha Monica | C13: =AVERAGEIF(tblMonthlySales[Rep_ID],A13,tblMonthlySales[Monthly_Sales]) -> 3866.1911
... A51: =Raw_Reps!A51 -> 321990 | B51: =Raw_Reps!B51 -> Dawna Agnew | C51: =AVERAGEIF(tblMonthlySales[Rep_ID],A51,tblMonthlySales[Monthly_Sales]) -> 17867.344

Sheet Raw_Orders
A1: id | B1: account_id | C1: occurred_at | D1: standard_qty | E1: gloss_qty | F1: poster_qty | G1: total | H1: standard_amt_usd | I1: gloss_amt_usd | J1: poster_amt_usd | K1: total_amt_usd
A2: 1 | B2: 1001 | C2: 42283.73 | D2: 123 | E2: 22 | F2: 24 | G2: 169 | H2: 613.77 | I2: 164.78 | J2: 194.88 | K2: 973.43
A3: 2 | B3: 1001 | C3: 42313.149 | D3: 190 | E3: 41 | F3: 57 | G3: 288 | H3: 948.1 | I3: 307.09 | J3: 462.84 | K3: 1718.03
A4: 3 | B4: 1001 | C4: 42342.182 | D4: 85 | E4: 47 | F4: 0 | G4: 132 | H4: 424.15 | I4: 352.03 | J4: 0 | K4: 776.18
A5: 4 | B5: 1001 | C5: 42371.054 | D5: 144 | E5: 32 | F5: 0 | G5: 176 | H5: 718.56 | I5: 239.68 | J5: 0 | K5: 958.24
A6: 5 | B6: 1001 | C6: 42401.811 | D6: 108 | E6: 29 | F6: 28 | G6: 165 | H6: 538.92 | I6: 217.21 | J6: 227.36 | K6: 983.49
A7: 6 | B7: 1001 | C7: 42431.646 | D7: 103 | E7: 24 | F7: 46 | G7: 173 | H7: 513.97 | I7: 179.76 | J7: 373.52 | K7: 1067.25
A8: 7 | B8: 1001 | C8: 42461.472 | D8: 101 | E8: 33 | F8: 92 | G8: 226 | H8: 503.99 | I8: 247.17 | J8: 747.04 | K8: 1498.2
A9: 8 | B9: 1001 | C9: 42491.664 | D9: 95 | E9: 47 | F9: 151 | G9: 293 | H9: 474.05 | I9: 352.03 | J9: 1226.12 | K9: 2052.2
A10: 9 | B10: 1001 | C10: 42521.891 | D10: 91 | E10: 16 | F10: 22 | G10: 129 | H10: 454.09 | I10: 119.84 | J10: 178.64 | K10: 752.57
A11: 10 | B11: 1001 | C11: 42551.522 | D11: 94 | E11: 46 | F11: 8 | G11: 148 | H11: 469.06 | I11: 344.54 | J11: 64.96 | K11: 878.56
A12: 11 | B12: 1001 | C12: 42581.143 | D12: 101 | E12: 36 | F12: 0 | G12: 137 | H12: 503.99 | I12: 269.64 | J12: 0 | K12: 773.63
A13: 12 | B13: 1001 | C13: 42610.301 | D13: 124 | E13: 33 | F13: 39 | G13: 196 | H13: 618.76 | I13: 247.17 | J13: 316.68 | K13: 1182.61
... A4051: 4050 | B4051: 4281 | C4051: 42402.321 | D4051: 304 | E4051: 153 | F4051: 19 | G4051: 476 | H4051: 1516.96 | I4051: 1145.97 | J4051: 154.28 | K4051: 2817.21

Sheet Raw_Accounts
A1: id | B1: name | C1: website | D1: lat | E1: long | F1: primary_poc | G1: sales_rep_id
A2: 1001 | B2: Walmart | C2: www.walmart.com | D2: 40.238496 | E2: -75.103297 | F2: Tamara Tuma | G2: 321500
A3: 1011 | B3: Exxon Mobil | C3: www.exxonmobil.com | D3: 41.169156 | E3: -73.849374 | F3: Sung Shields | G3: 321510
A4: 1021 | B4: Apple | C4: www.apple.com | D4: 42.290495 | E4: -76.084009 | F4: Jodee Lupo | G4: 321520
A5: 1031 | B5: Berkshire Hathaway | C5: www.berkshirehathaway.com | D5: 40.949021 | E5: -75.763898 | F5: Serafina Banda | G5: 321530
A6: 1041 | B6: McKesson | C6: www.mckesson.com | D6: 42.217093 | E6: -75.284998 | F6: Angeles Crusoe | G6: 321540
A7: 1051 | B7: UnitedHealth Group | C7: www.unitedhealthgroup.com | D7: 40.087925 | E7: -75.575694 | F7: Savanna Gayman | G7: 321550
A8: 1061 | B8: CVS Health | C8: www.cvshealth.com | D8: 41.467796 | E8: -73.767636 | F8: Anabel Haskell | G8: 321560
A9: 1071 | B9: General Motors | C9: www.gm.com | D9: 40.805518 | E9: -76.710181 | F9: Barrie Omeara | G9: 321570
A10: 1081 | B10: Ford Motor | C10: www.ford.com | D10: 41.113942 | E10: -75.854225 | F10: Kym Hagerman | G10: 321580
A11: 1091 | B11: AT&T | C11: www.att.com | D11: 42.497463 | E11: -74.902712 | F11: Jamel Mosqueda | G11: 321590
A12: 1101 | B12: General Electric | C12: www.ge.com | D12: 41.169712 | E12: -77.297132 | F12: Parker Hoggan | G12: 321600
A13: 1111 | B13: AmerisourceBergen | C13: www.amerisourcebergen.com | D13: 41.911469 | E13: -74.476208 | F13: Tuan Trainer | G13: 321610
... A352: 4501 | B352: SpartanNash | C352: www.spartannash.com | D352: 45.555651 | E352: -122.65714 | F352: Jewell Likes | G352: 321970

Sheet Raw_Reps
A1: id | B1: name | C1: region_id
A2: 321500 | B2: Samuel Racine | C2: 1
A3: 321510 | B3: Eugena Esser | C3: 1
A4: 321520 | B4: Michel Averette | C4: 1
A5: 321530 | B5: Renetta Carew | C5: 1
A6: 321540 | B6: Cara Clarke | C6: 1
A7: 321550 | B7: Lavera Oles | C7: 1
A8: 321560 | B8: Elba Felder | C8: 1
A9: 321570 | B9: Shawanda Selke | C9: 1
A10: 321580 | B10: Sibyl Lauria | C10: 1
A11: 321590 | B11: Necole Victory | C11: 1
A12: 321600 | B12: Ernestine Pickron | C12: 1
A13: 321610 | B13: Ayesha Monica | C13: 1
... A51: 321990 | B51: Dawna Agnew | C51: 4

Sheet Raw_Regions
A1: id | B1: name
A2: 1 | B2: Northeast
A3: 2 | B3: Midwest
A4: 3 | B4: Southeast
A5: 4 | B5: West
